{
  "rule_id": "584633040848949248",
  "scope": [
    "enterprise"
  ],
  "source_url": "https://learn-jdm.jd.com/knowledge/rule/detail?ruleId=584633040848949248",
  "search": {
    "title": "京东开放平台生鲜牛排类商品管理规则",
    "summary": "京东开放平台生鲜牛排类商品管理规范",
    "created": "2020-06-03",
    "modified": "2025-03-24",
    "url": "https://rule.jd.com/rule/ruleDetail.action?ruleId=584633040848949248&type=0&btype=1"
  },
  "detail": {
    "labelNames": "",
    "pv": "1",
    "endLabelIds": "5392",
    "endLabelNames": "质量标准",
    "title": "京东开放平台生鲜牛排类商品管理规则",
    "followRuleId": "3810",
    "content": "<p style=\"line-height: 200%; margin: 0cm 0cm 0.0001pt; font-size: 10.5pt; font-family: 等线;\" align=\"center\"><strong><span style=\"font-size: 10.0pt; line-height: 200%; font-family: 微软雅黑, sans-serif; color: black;\">第一章 目的</span></strong></p>\n<p style=\"text-indent: 21pt; line-height: 200%; margin: 0cm 0cm 0.0001pt; text-align: justify; font-size: 10.5pt; font-family: 等线;\"><span style=\"font-size: 10.0pt; line-height: 200%; font-family: 微软雅黑, sans-serif;\">为规范京东开放平台生鲜牛排类商品命名和商品页面发布信息，明确商品执行标准，使消费者可以清晰了解各类商品真实属性，避免因商家不当发布商品信息、虚假宣传引起消费者<span style=\"color: black;\">不良体验，特制定本标准。</span></span></p>\n<p style=\"line-height: 200%; margin: 0cm 0cm 0.0001pt; font-size: 10.5pt; font-family: 等线;\" align=\"center\"><strong><span style=\"font-size: 10.0pt; line-height: 200%; font-family: 微软雅黑, sans-serif; color: black;\">第二章 范围</span></strong></p>\n<p style=\"text-indent: 21pt; line-height: 200%; margin: 0cm 0cm 0.0001pt; text-align: justify; font-size: 10.5pt; font-family: 等线;\"><span style=\"font-size: 10.0pt; line-height: 200%; font-family: 微软雅黑, sans-serif; color: black;\">京东开放平台销售的各类牛排商品。本标准不包含使用碎肉、肉糜为原料加工的商品。</span></p>\n<p style=\"text-indent: 21pt; line-height: 200%; margin: 0cm 0cm 0.0001pt; text-align: justify; font-size: 10.5pt; font-family: 等线;\"><span style=\"font-size: 10.0pt; line-height: 200%; font-family: 微软雅黑, sans-serif;\">&nbsp;</span></p>\n<p style=\"line-height: 200%; margin: 0cm 0cm 0.0001pt; font-size: 10.5pt; font-family: 等线; text-align: center;\" align=\"center\"><strong><span style=\"font-size: 10.0pt; line-height: 200%; font-family: 微软雅黑, sans-serif; color: black;\">&nbsp; &nbsp; &nbsp; &nbsp;第三章 参考标准</span></strong></p>\n<p style=\"text-indent: 21pt; line-height: 200%; margin: 0cm 0cm 0.0001pt; text-align: justify; font-size: 10.5pt; font-family: 等线;\"><span style=\"font-size: 10.0pt; line-height: 200%; font-family: 微软雅黑, sans-serif; color: black;\">GB 2707&nbsp;</span><span style=\"font-size: 10.0pt; line-height: 200%; font-family: 微软雅黑, sans-serif; color: black;\">食品安全国家标准 鲜(冻)畜、禽商品</span></p>\n<p style=\"text-indent: 21pt; line-height: 200%; margin: 0cm 0cm 0.0001pt; text-align: justify; font-size: 10.5pt; font-family: 等线;\"><span style=\"font-size: 10.0pt; line-height: 200%; font-family: 微软雅黑, sans-serif; color: black;\">GB/T 17238 </span><span style=\"font-size: 10.0pt; line-height: 200%; font-family: 微软雅黑, sans-serif; color: black;\">鲜、冻分割牛肉</span></p>\n<p style=\"text-indent: 21pt; line-height: 200%; margin: 0cm 0cm 0.0001pt; text-align: justify; font-size: 10.5pt; font-family: 等线;\"><span style=\"font-size: 10.0pt; line-height: 200%; font-family: 微软雅黑, sans-serif; color: black;\">GB/T9960&nbsp;</span><span style=\"font-size: 10.0pt; line-height: 200%; font-family: 微软雅黑, sans-serif; color: black;\">鲜、冻四分体牛肉</span></p>\n<p style=\"text-indent: 21pt; line-height: 200%; margin: 0cm 0cm 0.0001pt; text-align: justify; font-size: 10.5pt; font-family: 等线;\"><span style=\"font-size: 10.0pt; line-height: 200%; font-family: 微软雅黑, sans-serif; color: black;\">GB/T 27643 </span><span style=\"font-size: 10.0pt; line-height: 200%; font-family: 微软雅黑, sans-serif; color: black;\">牛胴体及鲜肉分割</span></p>\n<p style=\"text-indent: 21pt; line-height: 200%; margin: 0cm 0cm 0.0001pt; text-align: justify; font-size: 10.5pt; font-family: 等线;\"><span style=\"font-size: 10.0pt; line-height: 200%; font-family: 微软雅黑, sans-serif; color: black;\">GB/T 29392 </span><span style=\"font-size: 10.0pt; line-height: 200%; font-family: 微软雅黑, sans-serif; color: black;\">普通肉牛上脑、眼肉、外脊、里脊等级划分</span></p>\n<p style=\"text-indent: 21pt; line-height: 200%; margin: 0cm 0cm 0.0001pt; text-align: justify; font-size: 10.5pt; font-family: 等线;\"><span style=\"font-size: 10.0pt; line-height: 200%; font-family: 微软雅黑, sans-serif; color: black;\">NY/T 676&nbsp;&nbsp;</span><span style=\"font-size: 10.0pt; line-height: 200%; font-family: 微软雅黑, sans-serif; color: black;\">牛肉等级规格</span></p>\n<p style=\"text-indent: 21pt; line-height: 200%; margin: 0cm 0cm 0.0001pt; text-align: justify; font-size: 10.5pt; font-family: 等线;\"><span style=\"font-size: 10.0pt; line-height: 200%; font-family: 微软雅黑, sans-serif; color: black;\">NY/T 3379&nbsp;</span><span style=\"font-size: 10.0pt; line-height: 200%; font-family: 微软雅黑, sans-serif; color: black;\">牛肉分级</span></p>\n<p style=\"text-indent: 21pt; line-height: 200%; margin: 0cm 0cm 0.0001pt; text-align: justify; font-size: 10.5pt; font-family: 等线;\"><span style=\"font-size: 10.0pt; line-height: 200%; font-family: 微软雅黑, sans-serif; color: black;\">SB/T 10379&nbsp;</span><span style=\"font-size: 10.0pt; line-height: 200%; font-family: 微软雅黑, sans-serif; color: black;\">速冻调制食品</span></p>\n<p style=\"text-indent: 21pt; line-height: 200%; margin: 0cm 0cm 0.0001pt; text-align: justify; font-size: 10.5pt; font-family: 等线;\"><span style=\"font-size: 10.0pt; line-height: 200%; font-family: 微软雅黑, sans-serif; color: black;\">SB/T 10482&nbsp;</span><span style=\"font-size: 10.0pt; line-height: 200%; font-family: 微软雅黑, sans-serif; color: black;\">预制肉类食品质量安全要求</span></p>\n<p style=\"text-indent: 21pt; line-height: 200%; margin: 0cm 0cm 0.0001pt; text-align: justify; font-size: 10.5pt; font-family: 等线;\"><span style=\"font-size: 10.0pt; line-height: 200%; font-family: 微软雅黑, sans-serif; color: black;\">GB 2760&nbsp;</span><span style=\"font-size: 10.0pt; line-height: 200%; font-family: 微软雅黑, sans-serif; color: black;\">食品安全国家标准 食品添加剂使用标准</span></p>\n<p style=\"text-indent: 21pt; line-height: 200%; margin: 0cm 0cm 0.0001pt; text-align: justify; font-size: 10.5pt; font-family: 等线;\"><span style=\"font-size: 10.0pt; line-height: 200%; font-family: 微软雅黑, sans-serif; color: black;\">GB 2762&nbsp;</span><span style=\"font-size: 10.0pt; line-height: 200%; font-family: 微软雅黑, sans-serif; color: black;\">食品安全国家标准 食品种污染物限量</span></p>\n<p style=\"text-indent: 21pt; line-height: 200%; margin: 0cm 0cm 0.0001pt; text-align: justify; font-size: 10.5pt; font-family: 等线;\"><span style=\"font-size: 10.0pt; line-height: 200%; font-family: 微软雅黑, sans-serif; color: black;\">GB 7718&nbsp;</span><span style=\"font-size: 10.0pt; line-height: 200%; font-family: 微软雅黑, sans-serif; color: black;\">食品安全国家标准 预包装食品标签通则</span></p>\n<p style=\"text-indent: 21pt; line-height: 200%; margin: 0cm 0cm 0.0001pt; text-align: justify; font-size: 10.5pt; font-family: 等线;\"><span style=\"font-size: 10.0pt; line-height: 200%; font-family: 微软雅黑, sans-serif; color: black;\">GB 28050&nbsp;</span><span style=\"font-size: 10.0pt; line-height: 200%; font-family: 微软雅黑, sans-serif; color: black;\">食品安全国家标准 预包装食品营养标签通则</span></p>\n<p style=\"text-indent: 21pt; line-height: 200%; margin: 0cm 0cm 0.0001pt; text-align: justify; font-size: 10.5pt; font-family: 等线;\"><span style=\"font-size: 10.0pt; line-height: 200%; font-family: 微软雅黑, sans-serif; color: black;\">QB/T 5442</span><span style=\"font-size: 10.0pt; line-height: 200%; font-family: 微软雅黑, sans-serif; color: black;\">牛排</span></p>\n<p style=\"text-indent: 21pt; line-height: 200%; margin: 0cm 0cm 0.0001pt; text-align: justify; font-size: 10.5pt; font-family: 等线;\"><span style=\"font-size: 10.0pt; line-height: 200%; font-family: 微软雅黑, sans-serif; color: black;\">QB/T 5443</span><span style=\"font-size: 10.0pt; line-height: 200%; font-family: 微软雅黑, sans-serif; color: black;\">牛排质量等级</span></p>\n<p style=\"text-indent: 21pt; line-height: 200%; margin: 0cm 0cm 0.0001pt; text-align: justify; font-size: 10.5pt; font-family: 等线;\"><span style=\"font-size: 10.0pt; line-height: 200%; font-family: 微软雅黑, sans-serif; color: black;\">同时参考恒都、皓月、元盛、东方万旗、天谱乐食、中荣、呼伦贝尔肉业、美享时刻、大希地牛排、如意三宝、浙江好牛、顶诺食品、牛豪鲜、小牛凯西等京东平台合作伙伴企业内控标准。</span></p>\n<p style=\"text-indent: 21pt; line-height: 200%; margin: 0cm 0cm 0.0001pt; text-align: justify; font-size: 10.5pt; font-family: 等线;\"><span style=\"font-size: 10.0pt; line-height: 200%; font-family: 微软雅黑, sans-serif;\">&nbsp;</span></p>\n<p style=\"line-height: 200%; margin: 0cm 0cm 0.0001pt; font-size: 10.5pt; font-family: 等线;\" align=\"center\"><strong><span style=\"font-size: 10.0pt; line-height: 200%; font-family: 微软雅黑, sans-serif; color: black;\">&nbsp; &nbsp;第四章 术语定义</span></strong></p>\n<p style=\"text-indent: 21pt; line-height: 200%; margin: 0cm 0cm 0.0001pt; text-align: justify; font-size: 10.5pt; font-family: 等线;\"><strong><span style=\"font-size: 10.0pt; line-height: 200%; font-family: 微软雅黑, sans-serif; color: black;\">（一）牛排</span></strong></p>\n<p style=\"text-indent: 21pt; line-height: 200%; margin: 0cm 0cm 0.0001pt; text-align: justify; font-size: 10.5pt; font-family: 等线;\"><span style=\"font-size: 10.0pt; line-height: 200%; font-family: 微软雅黑, sans-serif; color: black;\">以鲜、冻分割牛肉（带骨或不带骨）为原料，经修整、腌制（或不腌制）、成型（或不成型）、速冻（或不速冻）、切片等工艺制作的块状肉制品。以肉的特定部位名称命名的牛排商品必须采用与之对应部位的原料肉制作，非特定部位原料肉制作的牛排不能以肉的部位命名。</span></p>\n<p style=\"text-indent: 21pt; line-height: 200%; margin: 0cm 0cm 0.0001pt; text-align: justify; font-size: 10.5pt; font-family: 等线;\"><strong><span style=\"font-size: 10.0pt; line-height: 200%; font-family: 微软雅黑, sans-serif; color: black;\">（二）原切牛排</span></strong></p>\n<p style=\"text-indent: 21pt; line-height: 200%; margin: 0cm 0cm 0.0001pt; text-align: justify; font-size: 10.5pt; font-family: 等线;\"><span style=\"font-size: 10.0pt; line-height: 200%; font-family: 微软雅黑, sans-serif; color: black;\">以鲜、冻分割带骨（或不带骨）的整块牛肉为原料，经修整、速冻（或不速冻）、切片等工艺制作的牛排，仅为原肉切割，不添加任何其他配料。</span></p>\n<p style=\"text-indent: 21pt; line-height: 200%; margin: 0cm 0cm 0.0001pt; text-align: justify; font-size: 10.5pt; font-family: 等线;\"><strong><span style=\"font-size: 10.0pt; line-height: 200%; font-family: 微软雅黑, sans-serif; color: black;\">（三）静腌调理牛排</span></strong></p>\n<p style=\"text-indent: 21pt; line-height: 200%; margin: 0cm 0cm 0.0001pt; text-align: justify; font-size: 10.5pt; font-family: 等线;\"><span style=\"font-size: 10.0pt; line-height: 200%; font-family: 微软雅黑, sans-serif; color: black;\">以鲜、冻分割带骨（或不带骨）的整块牛肉为原料，经修整、速冻（或不速冻）、切片，静置于调味液浸泡入味等工艺制作的牛排。静腌调理牛排一般为原切牛排调味制成。</span></p>\n<p style=\"text-indent: 21pt; line-height: 200%; margin: 0cm 0cm 0.0001pt; text-align: justify; font-size: 10.5pt; font-family: 等线;\"><strong><span style=\"font-size: 10.0pt; line-height: 200%; font-family: 微软雅黑, sans-serif; color: black;\">（四）整切调理牛排</span></strong></p>\n<p style=\"text-indent: 21pt; line-height: 200%; margin: 0cm 0cm 0.0001pt; text-align: justify; font-size: 10.5pt; font-family: 等线;\"><span style=\"font-size: 10.0pt; line-height: 200%; font-family: 微软雅黑, sans-serif; color: black;\">以鲜、冻分割带骨（或不带骨）的整块牛肉为原料，经修整、注射、滚揉、整形、速冻（或不速冻）、切片等工艺制作的牛排。</span></p>\n<p style=\"text-indent: 21pt; line-height: 200%; margin: 0cm 0cm 0.0001pt; text-align: justify; font-size: 10.5pt; font-family: 等线;\"><strong><span style=\"font-size: 10.0pt; line-height: 200%; font-family: 微软雅黑, sans-serif; color: black;\">（五）加工调理牛排</span></strong></p>\n<p style=\"text-indent: 21pt; line-height: 200%; margin: 0cm 0cm 0.0001pt; text-align: justify; font-size: 10.5pt; font-family: 等线;\"><span style=\"font-size: 10.0pt; line-height: 200%; font-family: 微软雅黑, sans-serif; color: black;\">以鲜、冻分割带骨（或不带骨）的牛肉为原料，经去筋、去油、注射、滚揉、塑性（谷氨酰胺转氨酶催化粘合）、速冻（或不速冻）、切片工艺加工而成的牛排。</span></p>\n<p style=\"text-indent: 21pt; line-height: 200%; margin: 0cm 0cm 0.0001pt; text-align: justify; font-size: 10.5pt; font-family: 等线;\">&nbsp;</p>\n<p style=\"line-height: 200%; margin: 0cm 0cm 0.0001pt; font-size: 10.5pt; font-family: 等线;\" align=\"center\"><strong><span style=\"font-size: 10.0pt; line-height: 200%; font-family: 微软雅黑, sans-serif; color: black;\">第五章 分类</span></strong></p>\n<p style=\"text-indent: 21pt; line-height: 200%; margin: 0cm 0cm 0.0001pt; text-align: justify; font-size: 10.5pt; font-family: 等线;\"><strong><span style=\"font-size: 10.0pt; line-height: 200%; font-family: 微软雅黑, sans-serif; color: black;\">（一）牛种产区或产地分类</span></strong></p>\n<p style=\"text-indent: 21pt; line-height: 200%; margin: 0cm 0cm 0.0001pt; text-align: justify; font-size: 10.5pt; font-family: 等线;\"><span style=\"font-size: 10.0pt; line-height: 200%; font-family: 微软雅黑, sans-serif; color: black;\">1</span><span style=\"font-size: 10.0pt; line-height: 200%; font-family: 微软雅黑, sans-serif; color: black;\">、国产牛种：渤海黑牛、延边牛、晋南牛、秦川牛、南阳牛、鲁西黄牛、蒙古牛等。</span></p>\n<p style=\"text-indent: 21pt; line-height: 200%; margin: 0cm 0cm 0.0001pt; text-align: justify; font-size: 10.5pt; font-family: 等线;\"><span style=\"font-size: 10.0pt; line-height: 200%; font-family: 微软雅黑, sans-serif; color: black;\">2</span><span style=\"font-size: 10.0pt; line-height: 200%; font-family: 微软雅黑, sans-serif; color: black;\">、进口牛种：美国安格斯牛、美国和牛；法国利木赞牛、夏洛莱牛、奥布拉克牛；瑞士西门塔尔牛；澳洲安格斯牛、澳洲和牛；日本和牛（神户肉牛属于该品种）；英国海福特牛、短角牛、安格斯牛；荷兰荷斯坦牛（黑白花牛）；意大利皮埃蒙特牛、契安尼娜牛；丹麦红牛；加拿大牛种等。</span></p>\n<p style=\"text-indent: 21pt; line-height: 200%; margin: 0cm 0cm 0.0001pt; text-align: justify; font-size: 10.5pt; font-family: 等线;\"><strong><span style=\"font-size: 10.0pt; line-height: 200%; font-family: 微软雅黑, sans-serif; color: black;\">（二）肉牛饲养方式分类</span></strong></p>\n<p style=\"text-indent: 21pt; line-height: 200%; margin: 0cm 0cm 0.0001pt; text-align: justify; font-size: 10.5pt; font-family: 等线;\"><span style=\"font-size: 10.0pt; line-height: 200%; font-family: 微软雅黑, sans-serif; color: black;\">1</span><span style=\"font-size: 10.0pt; line-height: 200%; font-family: 微软雅黑, sans-serif; color: black;\">、草饲肉牛：肉牛一般放养在牧场以新鲜牧草为主要食物来源直到成熟期，草饲牛肉特点为肉质精瘦，脂肪含量低，味道浓郁，肉质细嫩。</span></p>\n<p style=\"text-indent: 21pt; line-height: 200%; margin: 0cm 0cm 0.0001pt; text-align: justify; font-size: 10.5pt; font-family: 等线;\"><span style=\"font-size: 10.0pt; line-height: 200%; font-family: 微软雅黑, sans-serif; color: black;\">2</span><span style=\"font-size: 10.0pt; line-height: 200%; font-family: 微软雅黑, sans-serif; color: black;\">、谷饲肉牛：小牛食用牧草长到一定体重时，在饲养场通过以大麦、小麦、燕麦、高粱、玉米等谷物为原料的配方饲料进行饲喂到成熟期。谷饲牛肉的特点为肉质细嫩、多汁、浓郁、醇厚。</span></p>\n<p style=\"text-indent: 21pt; line-height: 200%; margin: 0cm 0cm 0.0001pt; text-align: justify; font-size: 10.5pt; font-family: 等线;\"><strong><span style=\"font-size: 10.0pt; line-height: 200%; font-family: 微软雅黑, sans-serif; color: black;\">（三）&nbsp;牛排常见部位分类</span></strong></p>\n<p style=\"text-indent: 21pt; line-height: 200%; margin: 0cm 0cm 0.0001pt; text-align: justify; font-size: 10.5pt; font-family: 等线;\"><strong><span style=\"font-size: 10.0pt; line-height: 200%; font-family: 微软雅黑, sans-serif; color: black;\">1</span></strong><strong><span style=\"font-size: 10.0pt; line-height: 200%; font-family: 微软雅黑, sans-serif; color: black;\">、西冷牛排（外脊）</span></strong><span style=\"font-size: 10.0pt; line-height: 200%; font-family: 微软雅黑, sans-serif; color: black;\">：以整块牛外脊为原料，制作的原切或调理牛排。西冷牛排肉外圈带一圈白色的肉筋，肉质厚实，口感偏硬，有嚼劲。</span></p>\n<p style=\"text-indent: 21pt; line-height: 200%; margin: 0cm 0cm 0.0001pt; text-align: justify; font-size: 10.5pt; font-family: 等线;\"><strong><span style=\"font-size: 10.0pt; line-height: 200%; font-family: 微软雅黑, sans-serif; color: black;\">2</span></strong><strong><span style=\"font-size: 10.0pt; line-height: 200%; font-family: 微软雅黑, sans-serif; color: black;\">、菲力牛排（内脊/牛柳）</span></strong><span style=\"font-size: 10.0pt; line-height: 200%; font-family: 微软雅黑, sans-serif; color: black;\">：以整块牛里脊为原料，制作的原切或调理牛排。菲力牛排瘦肉多，脂肪低，肉质鲜嫩。</span></p>\n<p style=\"text-indent: 21pt; line-height: 200%; margin: 0cm 0cm 0.0001pt; text-align: justify; font-size: 10.5pt; font-family: 等线;\"><strong><span style=\"font-size: 10.0pt; line-height: 200%; font-family: 微软雅黑, sans-serif; color: black;\">3</span></strong><strong><span style=\"font-size: 10.0pt; line-height: 200%; font-family: 微软雅黑, sans-serif; color: black;\">、T骨牛排（西冷和菲力）</span></strong><span style=\"font-size: 10.0pt; line-height: 200%; font-family: 微软雅黑, sans-serif; color: black;\">：同时兼有外脊与里脊原料，制作的原切或调理牛排。外形由T字形牛骨相连，同时兼有西冷牛排和菲力牛排的特点。</span></p>\n<p style=\"text-indent: 21pt; line-height: 200%; margin: 0cm 0cm 0.0001pt; text-align: justify; font-size: 10.5pt; font-family: 等线;\"><strong><span style=\"font-size: 10.0pt; line-height: 200%; font-family: 微软雅黑, sans-serif; color: black;\">4</span></strong><strong><span style=\"font-size: 10.0pt; line-height: 200%; font-family: 微软雅黑, sans-serif; color: black;\">、眼肉牛排（莎朗）</span></strong><span style=\"font-size: 10.0pt; line-height: 200%; font-family: 微软雅黑, sans-serif; color: black;\">：以整块牛眼肉为原料，制作的原切或调理牛排。眼肉牛排肉质柔软、多汁，肥瘦相间，有雪花纹脂肪分布。</span></p>\n<p style=\"text-indent: 21pt; line-height: 200%; margin: 0cm 0cm 0.0001pt; text-align: justify; font-size: 10.5pt; font-family: 等线;\"><strong><span style=\"font-size: 10.0pt; line-height: 200%; font-family: 微软雅黑, sans-serif; color: black;\">5</span></strong><strong><span style=\"font-size: 10.0pt; line-height: 200%; font-family: 微软雅黑, sans-serif; color: black;\">、战斧牛排（带骨眼肉）</span></strong><span style=\"font-size: 10.0pt; line-height: 200%; font-family: 微软雅黑, sans-serif; color: black;\">：以带骨的眼肉为原料，制作的原切或调理牛排，因保留肋骨形似斧头得名。战斧牛排具有眼肉的肉质柔软、多汁的特点。</span></p>\n<p style=\"text-indent: 21pt; line-height: 200%; margin: 0cm 0cm 0.0001pt; text-align: justify; font-size: 10.5pt; font-family: 等线;\"><strong><span style=\"font-size: 10.0pt; line-height: 200%; font-family: 微软雅黑, sans-serif; color: black;\">6</span></strong><strong><span style=\"font-size: 10.0pt; line-height: 200%; font-family: 微软雅黑, sans-serif; color: black;\">、上脑牛排</span></strong><span style=\"font-size: 10.0pt; line-height: 200%; font-family: 微软雅黑, sans-serif; color: black;\">：以整块牛上脑肉为原料，制作的原切或调理牛排。上脑牛排肉质较硬，口感有嚼劲。</span></p>\n<p style=\"text-indent: 21pt; line-height: 200%; margin: 0cm 0cm 0.0001pt; text-align: justify; font-size: 10.5pt; font-family: 等线;\"><strong><span style=\"font-size: 10.0pt; line-height: 200%; font-family: 微软雅黑, sans-serif; color: black;\">7</span></strong><strong><span style=\"font-size: 10.0pt; line-height: 200%; font-family: 微软雅黑, sans-serif; color: black;\">、板腱牛排</span></strong><span style=\"font-size: 10.0pt; line-height: 200%; font-family: 微软雅黑, sans-serif; color: black;\">：以整块板腱为原料，制作的原切或调理牛排。板腱牛排一般中间有一根筋，有雪花纹路，肉质鲜嫩多汁。</span></p>\n<p style=\"text-indent: 21pt; line-height: 200%; margin: 0cm 0cm 0.0001pt; text-align: justify; font-size: 10.5pt; font-family: 等线;\">&nbsp;</p>\n<p style=\"line-height: 200%; margin: 0cm 0cm 0.0001pt; font-size: 10.5pt; font-family: 等线;\" align=\"center\"><strong><span style=\"font-size: 10.0pt; line-height: 200%; font-family: 微软雅黑, sans-serif; color: black;\">&nbsp; &nbsp; &nbsp; &nbsp;第六章 商品等级</span></strong></p>\n<p style=\"text-indent: 21pt; line-height: 200%; margin: 0cm 0cm 0.0001pt; text-align: justify; font-size: 10.5pt; font-family: 等线;\"><span style=\"font-size: 10.0pt; line-height: 200%; font-family: 微软雅黑, sans-serif; color: black;\"><strong>（一）</strong>普通原料牛肉等级按照NY/T676《牛肉等级规格》的标准执行，所有声称的特级、优级商品必须有相应等级证明材料，否则不得声称符合相应等级。</span></p>\n<p style=\"text-indent: 21pt; line-height: 200%; margin: 0cm 0cm 0.0001pt; text-align: justify; font-size: 10.5pt; font-family: 等线;\"><span style=\"font-size: 10.0pt; line-height: 200%; font-family: 微软雅黑, sans-serif; color: black;\"><strong>（二）</strong>分割部位牛肉等级按照NY/T 3379《牛肉分级》标准，所有声称的S、A、B、C级牛肉，须按照标准测评出具符合相应级别的测评报告，否则不得声称符合相应等级。</span></p>\n<p style=\"text-indent: 21pt; line-height: 200%; margin: 0cm 0cm 0.0001pt; text-align: justify; font-size: 10.5pt; font-family: 等线;\"><span style=\"font-size: 10.0pt; line-height: 200%; font-family: 微软雅黑, sans-serif; color: black;\"><strong>（三）</strong>普通肉牛上脑、眼肉、外脊、里脊的等级划分，按照GB/T29392《普通肉牛上脑、眼肉、外脊、里脊的等级划分》执行，所有声称的具备级别的商品，须按照标准测评出具符合相应级别的证明材料，否则不得声称符合相应等级。</span></p>\n<p style=\"text-indent: 21pt; line-height: 200%; margin: 0cm 0cm 0.0001pt; text-align: justify; font-size: 10.5pt; font-family: 等线;\"><span style=\"font-size: 10.0pt; line-height: 200%; font-family: 微软雅黑, sans-serif; color: black;\"><strong>（四）</strong>小牛肉、小白牛肉、雪花肉的分级，平台商家有声称的，须提供商品分级标准，并提供符合等级的测评证明材料，否则不得声称符合相应等级。</span></p>\n<p style=\"text-indent: 21pt; line-height: 200%; margin: 0cm 0cm 0.0001pt; text-align: justify; font-size: 10.5pt; font-family: 等线;\"><span style=\"font-size: 10.0pt; line-height: 200%; font-family: 微软雅黑, sans-serif; color: black;\"><strong>（五）</strong>进口原切牛排商品按照出口国规定进行等级划分，若该出口国无等级划分规定则不做等级划分。</span></p>\n<p style=\"text-indent: 21pt; line-height: 200%; margin: 0cm 0cm 0.0001pt; text-align: justify; font-size: 10.5pt; font-family: 等线;\"><span style=\"font-size: 10.0pt; line-height: 200%; font-family: 微软雅黑, sans-serif; color: black;\"><strong>（六）</strong>相关企业制定企业标准的，按照企业标准进行等级划分的，应提供符合企业标准等级的测评证明材料，否则不得声称符合相应等级。</span></p>\n<p style=\"text-indent: 21pt; line-height: 200%; margin: 0cm 0cm 0.0001pt; text-align: justify; font-size: 10.5pt; font-family: 等线;\">&nbsp;</p>\n<p style=\"text-align: center; line-height: 200%; margin: 0cm 0cm 0.0001pt; font-size: 10.5pt; font-family: 等线;\" align=\"center\"><strong><span style=\"font-size: 10.0pt; line-height: 200%; font-family: 微软雅黑, sans-serif; color: black;\">&nbsp; &nbsp; &nbsp; &nbsp;第七章 技术要求</span></strong></p>\n<p style=\"text-indent: 21pt; line-height: 200%; margin: 0cm 0cm 0.0001pt; text-align: justify; font-size: 10.5pt; font-family: 等线;\"><strong><span style=\"font-size: 10.0pt; line-height: 200%; font-family: 微软雅黑, sans-serif; color: black;\">（一）感官要求</span></strong></p>\n<p style=\"text-indent: 21pt; line-height: 200%; margin: 0cm 0cm 0.0001pt; text-align: justify; font-size: 10.5pt; font-family: 等线;\"><span style=\"font-size: 10.0pt; line-height: 200%; font-family: 微软雅黑, sans-serif; color: black;\">商品感官应符合表1的要求。</span></p>\n<p style=\"text-align: center; line-height: 200%; margin: 0cm 0cm 0.0001pt; font-size: 10.5pt; font-family: 等线;\" align=\"center\"><span style=\"font-size: 10.0pt; line-height: 200%; font-family: 微软雅黑, sans-serif; color: black;\">表1&nbsp;感官要求</span></p>\n<div align=\"center\">\n<table class=\"MsoNormalTable\" style=\"width: 417.95pt; border-collapse: collapse;\" border=\"0\" width=\"557\" cellspacing=\"0\" cellpadding=\"0\">\n<tbody>\n<tr style=\"height: 20.75pt;\">\n<td style=\"width: 35.4pt; border: solid windowtext 1.0pt; padding: 0cm 5.4pt 0cm 5.4pt; height: 20.75pt;\" rowspan=\"2\" width=\"47\">\n<p style=\"text-align: center; line-height: 200%; margin: 0cm 0cm 0.0001pt; font-size: 10.5pt; font-family: 等线;\" align=\"center\"><span style=\"font-size: 10.0pt; line-height: 200%; font-family: 微软雅黑, sans-serif; color: black;\">项目</span></p>\n</td>\n<td style=\"width: 382.55pt; border: solid windowtext 1.0pt; border-left: none; padding: 0cm 5.4pt 0cm 5.4pt; height: 20.75pt;\" colspan=\"2\" width=\"510\">\n<p style=\"text-align: center; line-height: 200%; margin: 0cm 0cm 0.0001pt; font-size: 10.5pt; font-family: 等线;\" align=\"center\"><span style=\"font-size: 10.0pt; line-height: 200%; font-family: 微软雅黑, sans-serif; color: black;\">指标</span></p>\n</td>\n</tr>\n<tr style=\"height: 26.6pt;\">\n<td style=\"width: 205.35pt; border-top: none; border-left: none; border-bottom: solid windowtext 1.0pt; border-right: solid windowtext 1.0pt; padding: 0cm 5.4pt 0cm 5.4pt; height: 26.6pt;\" width=\"274\">\n<p style=\"text-align: center; line-height: 200%; margin: 0cm 0cm 0.0001pt; font-size: 10.5pt; font-family: 等线;\" align=\"center\"><span style=\"font-size: 10.0pt; line-height: 200%; font-family: 微软雅黑, sans-serif; color: black;\">原切牛排</span></p>\n</td>\n<td style=\"width: 177.2pt; border-top: none; border-left: none; border-bottom: solid windowtext 1.0pt; border-right: solid windowtext 1.0pt; padding: 0cm 5.4pt 0cm 5.4pt; height: 26.6pt;\" width=\"236\">\n<p style=\"text-align: center; line-height: 200%; margin: 0cm 0cm 0.0001pt; font-size: 10.5pt; font-family: 等线;\" align=\"center\"><span style=\"font-size: 10.0pt; line-height: 200%; font-family: 微软雅黑, sans-serif; color: black;\">调理牛排</span></p>\n</td>\n</tr>\n<tr style=\"height: 3.75pt;\">\n<td style=\"width: 35.4pt; border: solid windowtext 1.0pt; border-top: none; padding: 0cm 5.4pt 0cm 5.4pt; height: 3.75pt;\" width=\"47\">\n<p style=\"line-height: 200%; margin: 0cm 0cm 0.0001pt; font-size: 10.5pt; font-family: 等线; text-align: center;\"><span style=\"font-size: 10.0pt; line-height: 200%; font-family: 微软雅黑, sans-serif; color: black;\">色泽</span></p>\n</td>\n<td style=\"width: 205.35pt; border-top: none; border-left: none; border-bottom: solid windowtext 1.0pt; border-right: solid windowtext 1.0pt; padding: 0cm 5.4pt 0cm 5.4pt; height: 3.75pt;\" width=\"274\">\n<p style=\"line-height: 200%; margin: 0cm 0cm 0.0001pt; font-size: 10.5pt; font-family: 等线; text-align: center;\"><span style=\"font-size: 10.0pt; line-height: 200%; font-family: 微软雅黑, sans-serif; color: black;\">肌肉色由鲜红色、深红色、浅红色至黑红色，脂肪色由洁白色、乳白色、浅黄色至黄色，商家有商品规格书标准的，应符合商品规格书标准</span></p>\n</td>\n<td style=\"width: 177.2pt; border-top: none; border-left: none; border-bottom: solid windowtext 1.0pt; border-right: solid windowtext 1.0pt; padding: 0cm 5.4pt 0cm 5.4pt; height: 3.75pt;\" width=\"236\">\n<p style=\"line-height: 200%; margin: 0cm 0cm 0.0001pt; font-size: 10.5pt; font-family: 等线; text-align: center;\"><span style=\"font-size: 10.0pt; line-height: 200%; font-family: 微软雅黑, sans-serif; color: black;\">不同配料、不同类型商品色泽应符合商家商品规格书的标准</span></p>\n</td>\n</tr>\n<tr style=\"height: 30.5pt;\">\n<td style=\"width: 35.4pt; border: solid windowtext 1.0pt; border-top: none; padding: 0cm 5.4pt 0cm 5.4pt; height: 30.5pt;\" width=\"47\">\n<p style=\"line-height: 200%; margin: 0cm 0cm 0.0001pt; font-size: 10.5pt; font-family: 等线; text-align: center;\"><span style=\"font-size: 10.0pt; line-height: 200%; font-family: 微软雅黑, sans-serif; color: black;\">风味</span></p>\n</td>\n<td style=\"width: 205.35pt; border-top: none; border-left: none; border-bottom: solid windowtext 1.0pt; border-right: solid windowtext 1.0pt; padding: 0cm 5.4pt 0cm 5.4pt; height: 30.5pt;\" width=\"274\">\n<p style=\"line-height: 200%; margin: 0cm 0cm 0.0001pt; font-size: 10.5pt; font-family: 等线; text-align: center;\"><span style=\"font-size: 10.0pt; line-height: 200%; font-family: 微软雅黑, sans-serif; color: black;\">有商品应有的风味，无异味</span></p>\n</td>\n<td style=\"width: 177.2pt; border-top: none; border-left: none; border-bottom: solid windowtext 1.0pt; border-right: solid windowtext 1.0pt; padding: 0cm 5.4pt 0cm 5.4pt; height: 30.5pt;\" width=\"236\">\n<p style=\"line-height: 200%; margin: 0cm 0cm 0.0001pt; font-size: 10.5pt; font-family: 等线; text-align: center;\"><span style=\"font-size: 10.0pt; line-height: 200%; font-family: 微软雅黑, sans-serif; color: black;\">不同配料商品应有符合商家商品规格书要求的风味</span></p>\n</td>\n</tr>\n<tr style=\"height: 30.9pt;\">\n<td style=\"width: 35.4pt; border: solid windowtext 1.0pt; border-top: none; padding: 0cm 5.4pt 0cm 5.4pt; height: 30.9pt;\" width=\"47\">\n<p style=\"line-height: 200%; margin: 0cm 0cm 0.0001pt; font-size: 10.5pt; font-family: 等线; text-align: center;\"><span style=\"font-size: 10.0pt; line-height: 200%; font-family: 微软雅黑, sans-serif; color: black;\">组织状态</span></p>\n</td>\n<td style=\"width: 205.35pt; border-top: none; border-left: none; border-bottom: solid windowtext 1.0pt; border-right: solid windowtext 1.0pt; padding: 0cm 5.4pt 0cm 5.4pt; height: 30.9pt;\" width=\"274\">\n<p style=\"line-height: 200%; margin: 0cm 0cm 0.0001pt; font-size: 10.5pt; font-family: 等线; text-align: center;\"><span style=\"font-size: 10.0pt; line-height: 200%; font-family: 微软雅黑, sans-serif; color: black;\">组织致密，有明显的肌肉纹理</span></p>\n</td>\n<td style=\"width: 177.2pt; border-top: none; border-left: none; border-bottom: solid windowtext 1.0pt; border-right: solid windowtext 1.0pt; padding: 0cm 5.4pt 0cm 5.4pt; height: 30.9pt;\" width=\"236\">\n<p style=\"line-height: 200%; margin: 0cm 0cm 0.0001pt; font-size: 10.5pt; font-family: 等线; text-align: center;\"><span style=\"font-size: 10.0pt; line-height: 200%; font-family: 微软雅黑, sans-serif; color: black;\">组织致密，无明显气孔，有可见的肌肉纹理</span></p>\n</td>\n</tr>\n<tr style=\"height: 31.25pt;\">\n<td style=\"width: 35.4pt; border: solid windowtext 1.0pt; border-top: none; padding: 0cm 5.4pt 0cm 5.4pt; height: 31.25pt;\" width=\"47\">\n<p style=\"line-height: 200%; margin: 0cm 0cm 0.0001pt; font-size: 10.5pt; font-family: 等线; text-align: center;\"><span style=\"font-size: 10.0pt; line-height: 200%; font-family: 微软雅黑, sans-serif; color: black;\">异物</span></p>\n</td>\n<td style=\"width: 382.55pt; border-top: none; border-left: none; border-bottom: solid windowtext 1.0pt; border-right: solid windowtext 1.0pt; padding: 0cm 5.4pt 0cm 5.4pt; height: 31.25pt;\" colspan=\"2\" width=\"510\">\n<p style=\"line-height: 200%; margin: 0cm 0cm 0.0001pt; font-size: 10.5pt; font-family: 等线; text-align: center;\"><span style=\"font-size: 10.0pt; line-height: 200%; font-family: 微软雅黑, sans-serif; color: black;\">无正常视力可见杂质，不得带伤斑、血瘀、血污、碎骨、病变组织、浮毛或其他杂质</span></p>\n</td>\n</tr>\n</tbody>\n</table>\n</div>\n<p style=\"text-indent: 21pt; line-height: 200%; margin: 0cm 0cm 0.0001pt; text-align: justify; font-size: 10.5pt; font-family: 等线;\"><strong><span style=\"font-size: 10.0pt; line-height: 200%; font-family: 微软雅黑, sans-serif; color: black;\">（二）理化指标</span></strong></p>\n<p style=\"text-indent: 21pt; line-height: 200%; margin: 0cm 0cm 0.0001pt; text-align: justify; font-size: 10.5pt; font-family: 等线;\"><span style=\"font-size: 10.0pt; line-height: 200%; font-family: 微软雅黑, sans-serif; color: black;\">理化指标应符合表2的规定。</span></p>\n<p style=\"text-align: center; line-height: 200%; margin: 0cm 0cm 0.0001pt; font-size: 10.5pt; font-family: 等线;\" align=\"center\"><span style=\"font-size: 10.0pt; line-height: 200%; font-family: 微软雅黑, sans-serif; color: black;\">表2&nbsp;理化指标</span></p>\n<div align=\"center\">\n<table class=\"MsoNormalTable\" style=\"width: 347.05pt; border-collapse: collapse;\" border=\"0\" width=\"463\" cellspacing=\"0\" cellpadding=\"0\">\n<tbody>\n<tr style=\"height: 19.55pt;\">\n<td style=\"width: 163.05pt; border: solid windowtext 1.0pt; padding: 0cm 5.4pt 0cm 5.4pt; height: 19.55pt;\" rowspan=\"2\" width=\"217\">\n<p style=\"text-align: center; line-height: 200%; margin: 0cm 0cm 0.0001pt; font-size: 10.5pt; font-family: 等线;\" align=\"center\"><span style=\"font-size: 10.0pt; line-height: 200%; font-family: 微软雅黑, sans-serif; color: black;\">项目</span></p>\n</td>\n<td style=\"width: 184.0pt; border: solid windowtext 1.0pt; border-left: none; padding: 0cm 5.4pt 0cm 5.4pt; height: 19.55pt;\" colspan=\"2\" width=\"245\">\n<p style=\"text-align: center; line-height: 200%; margin: 0cm 0cm 0.0001pt; font-size: 10.5pt; font-family: 等线;\" align=\"center\"><span style=\"font-size: 10.0pt; line-height: 200%; font-family: 微软雅黑, sans-serif; color: black;\">指标</span></p>\n</td>\n</tr>\n<tr style=\"height: 15.35pt;\">\n<td style=\"width: 91.85pt; border-top: none; border-left: none; border-bottom: solid windowtext 1.0pt; border-right: solid windowtext 1.0pt; padding: 0cm 5.4pt 0cm 5.4pt; height: 15.35pt;\" width=\"122\">\n<p style=\"text-align: center; line-height: 200%; margin: 0cm 0cm 0.0001pt; font-size: 10.5pt; font-family: 等线;\" align=\"center\"><span style=\"font-size: 10.0pt; line-height: 200%; font-family: 微软雅黑, sans-serif; color: black;\">原切牛排</span></p>\n</td>\n<td style=\"width: 92.15pt; border-top: none; border-left: none; border-bottom: solid windowtext 1.0pt; border-right: solid windowtext 1.0pt; padding: 0cm 5.4pt 0cm 5.4pt; height: 15.35pt;\" width=\"123\">\n<p style=\"text-align: center; line-height: 200%; margin: 0cm 0cm 0.0001pt; font-size: 10.5pt; font-family: 等线;\" align=\"center\"><span style=\"font-size: 10.0pt; line-height: 200%; font-family: 微软雅黑, sans-serif; color: black;\">调理牛排</span></p>\n</td>\n</tr>\n<tr style=\"height: 7.7pt;\">\n<td style=\"width: 163.05pt; border: solid windowtext 1.0pt; border-top: none; padding: 0cm 5.4pt 0cm 5.4pt; height: 7.7pt;\" width=\"217\">\n<p style=\"line-height: 200%; margin: 0cm 0cm 0.0001pt; font-size: 10.5pt; font-family: 等线; text-align: center;\"><span style=\"font-size: 10.0pt; line-height: 200%; font-family: 微软雅黑, sans-serif; color: black;\">水分/(g/100g)</span></p>\n</td>\n<td style=\"width: 91.85pt; border-top: none; border-left: none; border-bottom: solid windowtext 1.0pt; border-right: solid windowtext 1.0pt; padding: 0cm 5.4pt 0cm 5.4pt; height: 7.7pt;\" width=\"122\">\n<p style=\"line-height: 200%; margin: 0cm 0cm 0.0001pt; font-size: 10.5pt; font-family: 等线; text-align: center;\" align=\"right\"><span style=\"font-size: 10.0pt; line-height: 200%; font-family: 微软雅黑, sans-serif; color: black;\">&le;77</span></p>\n</td>\n<td style=\"width: 92.15pt; border-top: none; border-left: none; border-bottom: solid windowtext 1.0pt; border-right: solid windowtext 1.0pt; padding: 0cm 5.4pt 0cm 5.4pt; height: 7.7pt;\" width=\"123\">\n<p style=\"line-height: 200%; margin: 0cm 0cm 0.0001pt; font-size: 10.5pt; font-family: 等线; text-align: center;\" align=\"right\"><span style=\"font-size: 10.0pt; line-height: 200%; font-family: 微软雅黑, sans-serif; color: black;\">&le;82</span></p>\n</td>\n</tr>\n<tr style=\"height: 7.7pt;\">\n<td style=\"width: 163.05pt; border: solid windowtext 1.0pt; border-top: none; padding: 0cm 5.4pt 0cm 5.4pt; height: 7.7pt;\" width=\"217\">\n<p style=\"line-height: 200%; margin: 0cm 0cm 0.0001pt; font-size: 10.5pt; font-family: 等线; text-align: center;\"><span style=\"font-size: 10.0pt; line-height: 200%; font-family: 微软雅黑, sans-serif; color: black;\">蛋白质/(g/100g)</span></p>\n</td>\n<td style=\"width: 91.85pt; border-top: none; border-left: none; border-bottom: solid windowtext 1.0pt; border-right: solid windowtext 1.0pt; padding: 0cm 5.4pt 0cm 5.4pt; height: 7.7pt;\" width=\"122\">\n<p style=\"line-height: 200%; margin: 0cm 0cm 0.0001pt; font-size: 10.5pt; font-family: 等线; text-align: center;\" align=\"right\"><span style=\"font-size: 10.0pt; line-height: 200%; font-family: 微软雅黑, sans-serif; color: black;\">&mdash;&mdash;</span></p>\n</td>\n<td style=\"width: 92.15pt; border-top: none; border-left: none; border-bottom: solid windowtext 1.0pt; border-right: solid windowtext 1.0pt; padding: 0cm 5.4pt 0cm 5.4pt; height: 7.7pt;\" width=\"123\">\n<p style=\"line-height: 200%; margin: 0cm 0cm 0.0001pt; font-size: 10.5pt; font-family: 等线; text-align: center;\" align=\"right\"><span style=\"font-size: 10.0pt; line-height: 200%; font-family: 微软雅黑, sans-serif; color: black;\">&ge;13</span></p>\n</td>\n</tr>\n<tr style=\"height: 7.7pt;\">\n<td style=\"width: 163.05pt; border: solid windowtext 1.0pt; border-top: none; padding: 0cm 5.4pt 0cm 5.4pt; height: 7.7pt;\" width=\"217\">\n<p style=\"line-height: 200%; margin: 0cm 0cm 0.0001pt; font-size: 10.5pt; font-family: 等线; text-align: center;\"><span style=\"font-size: 10.0pt; line-height: 200%; font-family: 微软雅黑, sans-serif; color: black;\">淀粉/(g/100g)</span></p>\n</td>\n<td style=\"width: 91.85pt; border-top: none; border-left: none; border-bottom: solid windowtext 1.0pt; border-right: solid windowtext 1.0pt; padding: 0cm 5.4pt 0cm 5.4pt; height: 7.7pt;\" width=\"122\">\n<p style=\"line-height: 200%; margin: 0cm 0cm 0.0001pt; font-size: 10.5pt; font-family: 等线; text-align: center;\" align=\"right\"><span style=\"font-size: 10.0pt; line-height: 200%; font-family: 微软雅黑, sans-serif; color: black;\">&mdash;&mdash;</span></p>\n</td>\n<td style=\"width: 92.15pt; border-top: none; border-left: none; border-bottom: solid windowtext 1.0pt; border-right: solid windowtext 1.0pt; padding: 0cm 5.4pt 0cm 5.4pt; height: 7.7pt;\" width=\"123\">\n<p style=\"line-height: 200%; margin: 0cm 0cm 0.0001pt; font-size: 10.5pt; font-family: 等线; text-align: center;\" align=\"right\"><span style=\"font-size: 10.0pt; line-height: 200%; font-family: 微软雅黑, sans-serif; color: black;\">&le;1.5</span></p>\n</td>\n</tr>\n<tr style=\"height: 7.7pt;\">\n<td style=\"width: 163.05pt; border: solid windowtext 1.0pt; border-top: none; padding: 0cm 5.4pt 0cm 5.4pt; height: 7.7pt;\" width=\"217\">\n<p style=\"line-height: 200%; margin: 0cm 0cm 0.0001pt; font-size: 10.5pt; font-family: 等线; text-align: center;\"><span style=\"font-size: 10.0pt; line-height: 200%; font-family: 微软雅黑, sans-serif; color: black;\">挥发性盐基氮/（mg/100g）</span></p>\n</td>\n<td style=\"width: 91.85pt; border-top: none; border-left: none; border-bottom: solid windowtext 1.0pt; border-right: solid windowtext 1.0pt; padding: 0cm 5.4pt 0cm 5.4pt; height: 7.7pt;\" width=\"122\">\n<p style=\"line-height: 200%; margin: 0cm 0cm 0.0001pt; font-size: 10.5pt; font-family: 等线; text-align: center;\" align=\"right\"><span style=\"font-size: 10.0pt; line-height: 200%; font-family: 微软雅黑, sans-serif; color: black;\">&le;15</span></p>\n</td>\n<td style=\"width: 92.15pt; border-top: none; border-left: none; border-bottom: solid windowtext 1.0pt; border-right: solid windowtext 1.0pt; padding: 0cm 5.4pt 0cm 5.4pt; height: 7.7pt;\" width=\"123\">\n<p style=\"line-height: 200%; margin: 0cm 0cm 0.0001pt; font-size: 10.5pt; font-family: 等线; text-align: center;\" align=\"right\"><span style=\"font-size: 10.0pt; line-height: 200%; font-family: 微软雅黑, sans-serif; color: black;\">&mdash;&mdash;</span></p>\n</td>\n</tr>\n<tr style=\"height: 7.7pt;\">\n<td style=\"width: 163.05pt; border: solid windowtext 1.0pt; border-top: none; padding: 0cm 5.4pt 0cm 5.4pt; height: 7.7pt;\" width=\"217\">\n<p style=\"line-height: 200%; margin: 0cm 0cm 0.0001pt; font-size: 10.5pt; font-family: 等线; text-align: center;\" align=\"left\"><span style=\"font-size: 10.0pt; line-height: 200%; font-family: 微软雅黑, sans-serif; color: black;\">过氧化值(以脂肪计)/(g/100g)</span></p>\n</td>\n<td style=\"width: 91.85pt; border-top: none; border-left: none; border-bottom: solid windowtext 1.0pt; border-right: solid windowtext 1.0pt; padding: 0cm 5.4pt 0cm 5.4pt; height: 7.7pt;\" width=\"122\">\n<p style=\"line-height: 200%; margin: 0cm 0cm 0.0001pt; font-size: 10.5pt; font-family: 等线; text-align: center;\" align=\"right\"><span style=\"font-size: 10.0pt; line-height: 200%; font-family: 微软雅黑, sans-serif; color: black;\">&mdash;&mdash;</span></p>\n</td>\n<td style=\"width: 92.15pt; border-top: none; border-left: none; border-bottom: solid windowtext 1.0pt; border-right: solid windowtext 1.0pt; padding: 0cm 5.4pt 0cm 5.4pt; height: 7.7pt;\" width=\"123\">\n<p style=\"line-height: 200%; margin: 0cm 0cm 0.0001pt; font-size: 10.5pt; font-family: 等线; text-align: center;\" align=\"right\"><span style=\"font-size: 10.0pt; line-height: 200%; font-family: 微软雅黑, sans-serif; color: black;\">&le;0.25</span></p>\n</td>\n</tr>\n</tbody>\n</table>\n</div>\n<p style=\"text-indent: 21pt; line-height: 200%; margin: 0cm 0cm 0.0001pt; text-align: justify; font-size: 10.5pt; font-family: 等线;\"><strong><span style=\"font-size: 10.0pt; line-height: 200%; font-family: 微软雅黑, sans-serif; color: black;\">（三）食品安全指标</span></strong></p>\n<p style=\"text-indent: 21pt; line-height: 200%; margin: 0cm 0cm 0.0001pt; text-align: justify; font-size: 10.5pt; font-family: 等线;\"><span style=\"font-size: 10.0pt; line-height: 200%; font-family: 微软雅黑, sans-serif; color: black;\">1</span><span style=\"font-size: 10.0pt; line-height: 200%; font-family: 微软雅黑, sans-serif; color: black;\">、污染物指标：应符合GB2762中畜禽肉的规定。</span></p>\n<p style=\"text-indent: 21pt; line-height: 200%; margin: 0cm 0cm 0.0001pt; text-align: justify; font-size: 10.5pt; font-family: 等线;\"><span style=\"font-size: 10.0pt; line-height: 200%; font-family: 微软雅黑, sans-serif; color: black;\">2</span><span style=\"font-size: 10.0pt; line-height: 200%; font-family: 微软雅黑, sans-serif; color: black;\">、农药残留指标：应符合GB2763中畜禽肉的规定。</span></p>\n<p style=\"text-indent: 21pt; line-height: 200%; margin: 0cm 0cm 0.0001pt; text-align: justify; font-size: 10.5pt; font-family: 等线;\"><span style=\"font-size: 10.0pt; line-height: 200%; font-family: 微软雅黑, sans-serif; color: black;\">3</span><span style=\"font-size: 10.0pt; line-height: 200%; font-family: 微软雅黑, sans-serif; color: black;\">、微生物限量。</span></p>\n<p style=\"text-indent: 21pt; line-height: 200%; margin: 0cm 0cm 0.0001pt; text-align: justify; font-size: 10.5pt; font-family: 等线;\"><span style=\"font-size: 10.0pt; line-height: 200%; font-family: 微软雅黑, sans-serif; color: black;\">微生物限量应符合表3的规定。</span></p>\n<p style=\"text-align: center; line-height: 200%; margin: 0cm 0cm 0.0001pt; font-size: 10.5pt; font-family: 等线;\" align=\"center\"><span style=\"font-size: 10.0pt; line-height: 200%; font-family: 微软雅黑, sans-serif; color: black;\">表3&nbsp;微生物限量表</span></p>\n<div align=\"center\">\n<table class=\"MsoNormalTable\" style=\"width: 417.95pt; border-collapse: collapse;\" border=\"0\" width=\"557\" cellspacing=\"0\" cellpadding=\"0\">\n<tbody>\n<tr style=\"height: 9.35pt;\">\n<td style=\"width: 170.35pt; border: solid windowtext 1.0pt; padding: 0cm 5.4pt 0cm 5.4pt; height: 9.35pt;\" colspan=\"2\" rowspan=\"2\" width=\"227\">\n<p style=\"text-align: center; line-height: 200%; margin: 0cm 0cm 0.0001pt; font-size: 10.5pt; font-family: 等线;\" align=\"center\"><span style=\"font-size: 10.0pt; line-height: 200%; font-family: 微软雅黑, sans-serif; color: black;\">项目</span></p>\n</td>\n<td style=\"width: 142.05pt; border: solid windowtext 1.0pt; border-left: none; padding: 0cm 5.4pt 0cm 5.4pt; height: 9.35pt;\" colspan=\"4\" width=\"189\">\n<p style=\"text-align: center; line-height: 200%; margin: 0cm 0cm 0.0001pt; font-size: 10.5pt; font-family: 等线;\" align=\"center\"><span style=\"font-size: 10.0pt; line-height: 200%; font-family: 微软雅黑, sans-serif; color: black;\">采样方案及限量</span></p>\n</td>\n<td style=\"width: 105.55pt; border: solid windowtext 1.0pt; border-left: none; padding: 0cm 5.4pt 0cm 5.4pt; height: 9.35pt;\" rowspan=\"2\" width=\"141\">\n<p style=\"text-align: center; line-height: 200%; margin: 0cm 0cm 0.0001pt; font-size: 10.5pt; font-family: 等线;\" align=\"center\"><span style=\"font-size: 10.0pt; line-height: 200%; font-family: 微软雅黑, sans-serif; color: black;\">检验方法</span></p>\n</td>\n</tr>\n<tr style=\"height: 5.25pt;\">\n<td style=\"width: 1.0cm; border-top: none; border-left: none; border-bottom: solid windowtext 1.0pt; border-right: solid windowtext 1.0pt; padding: 0cm 5.4pt 0cm 5.4pt; height: 5.25pt;\" width=\"38\">\n<p style=\"text-align: center; line-height: 200%; margin: 0cm 0cm 0.0001pt; font-size: 10.5pt; font-family: 等线;\" align=\"center\"><span style=\"font-size: 10.0pt; line-height: 200%; font-family: 微软雅黑, sans-serif; color: black;\">n</span></p>\n</td>\n<td style=\"width: 1.0cm; border-top: none; border-left: none; border-bottom: solid windowtext 1.0pt; border-right: solid windowtext 1.0pt; padding: 0cm 5.4pt 0cm 5.4pt; height: 5.25pt;\" width=\"38\">\n<p style=\"text-align: center; line-height: 200%; margin: 0cm 0cm 0.0001pt; font-size: 10.5pt; font-family: 等线;\" align=\"center\"><span style=\"font-size: 10.0pt; line-height: 200%; font-family: 微软雅黑, sans-serif; color: black;\">c</span></p>\n</td>\n<td style=\"width: 42.55pt; border-top: none; border-left: none; border-bottom: solid windowtext 1.0pt; border-right: solid windowtext 1.0pt; padding: 0cm 5.4pt 0cm 5.4pt; height: 5.25pt;\" width=\"57\">\n<p style=\"text-align: center; line-height: 200%; margin: 0cm 0cm 0.0001pt; font-size: 10.5pt; font-family: 等线;\" align=\"center\"><span style=\"font-size: 10.0pt; line-height: 200%; font-family: 微软雅黑, sans-serif; color: black;\">m</span></p>\n</td>\n<td style=\"width: 42.8pt; border-top: none; border-left: none; border-bottom: solid windowtext 1.0pt; border-right: solid windowtext 1.0pt; padding: 0cm 5.4pt 0cm 5.4pt; height: 5.25pt;\" width=\"57\">\n<p style=\"text-align: center; line-height: 200%; margin: 0cm 0cm 0.0001pt; font-size: 10.5pt; font-family: 等线;\" align=\"center\"><span style=\"font-size: 10.0pt; line-height: 200%; font-family: 微软雅黑, sans-serif; color: black;\">M</span></p>\n</td>\n</tr>\n<tr style=\"height: 17.95pt;\">\n<td style=\"width: 49.65pt; border: solid windowtext 1.0pt; border-top: none; padding: 0cm 5.4pt 0cm 5.4pt; height: 17.95pt;\" rowspan=\"2\" width=\"66\">\n<p style=\"line-height: 200%; margin: 0cm 0cm 0.0001pt; font-size: 10.5pt; font-family: 等线; text-align: center;\"><span style=\"font-size: 10.0pt; line-height: 200%; font-family: 微软雅黑, sans-serif; color: black;\">原切牛排</span></p>\n</td>\n<td style=\"width: 120.7pt; border-top: none; border-left: none; border-bottom: solid windowtext 1.0pt; border-right: solid windowtext 1.0pt; padding: 0cm 5.4pt 0cm 5.4pt; height: 17.95pt;\" width=\"161\">\n<p style=\"line-height: 200%; margin: 0cm 0cm 0.0001pt; font-size: 10.5pt; font-family: 等线; text-align: center;\"><span style=\"font-size: 10.0pt; line-height: 200%; font-family: 微软雅黑, sans-serif; color: black;\">金黄色葡萄球菌（CFU/g）</span></p>\n</td>\n<td style=\"width: 1.0cm; border-top: none; border-left: none; border-bottom: solid windowtext 1.0pt; border-right: solid windowtext 1.0pt; padding: 0cm 5.4pt 0cm 5.4pt; height: 17.95pt;\" width=\"38\">\n<p style=\"text-align: center; line-height: 200%; margin: 0cm 0cm 0.0001pt; font-size: 10.5pt; font-family: 等线;\" align=\"center\"><span style=\"font-size: 10.0pt; line-height: 200%; font-family: 微软雅黑, sans-serif; color: black;\">5</span></p>\n</td>\n<td style=\"width: 1.0cm; border-top: none; border-left: none; border-bottom: solid windowtext 1.0pt; border-right: solid windowtext 1.0pt; padding: 0cm 5.4pt 0cm 5.4pt; height: 17.95pt;\" width=\"38\">\n<p style=\"text-align: center; line-height: 200%; margin: 0cm 0cm 0.0001pt; font-size: 10.5pt; font-family: 等线;\" align=\"center\"><span style=\"font-size: 10.0pt; line-height: 200%; font-family: 微软雅黑, sans-serif; color: black;\">1</span></p>\n</td>\n<td style=\"width: 42.55pt; border-top: none; border-left: none; border-bottom: solid windowtext 1.0pt; border-right: solid windowtext 1.0pt; padding: 0cm 5.4pt 0cm 5.4pt; height: 17.95pt;\" width=\"57\">\n<p style=\"text-align: center; line-height: 200%; margin: 0cm 0cm 0.0001pt; font-size: 10.5pt; font-family: 等线;\" align=\"center\"><span style=\"font-size: 10.0pt; line-height: 200%; font-family: 微软雅黑, sans-serif; color: black;\">1000</span></p>\n</td>\n<td style=\"width: 42.8pt; border-top: none; border-left: none; border-bottom: solid windowtext 1.0pt; border-right: solid windowtext 1.0pt; padding: 0cm 5.4pt 0cm 5.4pt; height: 17.95pt;\" width=\"57\">\n<p style=\"text-align: center; line-height: 200%; margin: 0cm 0cm 0.0001pt; font-size: 10.5pt; font-family: 等线;\" align=\"center\"><span style=\"font-size: 10.0pt; line-height: 200%; font-family: 微软雅黑, sans-serif; color: black;\">10000</span></p>\n</td>\n<td style=\"width: 105.55pt; border-top: none; border-left: none; border-bottom: solid windowtext 1.0pt; border-right: solid windowtext 1.0pt; padding: 0cm 5.4pt 0cm 5.4pt; height: 17.95pt;\" width=\"141\">\n<p style=\"line-height: 200%; margin: 0cm 0cm 0.0001pt; font-size: 10.5pt; font-family: 等线; text-align: center;\"><span style=\"font-size: 10.0pt; line-height: 200%; font-family: 微软雅黑, sans-serif; color: black;\">GB4789.10</span><span style=\"font-size: 10.0pt; line-height: 200%; font-family: 微软雅黑, sans-serif; color: black;\">平板计数法</span></p>\n</td>\n</tr>\n<tr style=\"height: 21.65pt;\">\n<td style=\"width: 120.7pt; border-top: none; border-left: none; border-bottom: solid windowtext 1.0pt; border-right: solid windowtext 1.0pt; padding: 0cm 5.4pt 0cm 5.4pt; height: 21.65pt;\" width=\"161\">\n<p style=\"line-height: 200%; margin: 0cm 0cm 0.0001pt; font-size: 10.5pt; font-family: 等线; text-align: center;\"><span style=\"font-size: 10.0pt; line-height: 200%; font-family: 微软雅黑, sans-serif; color: black;\">沙门氏菌（CFU/g）&nbsp;</span></p>\n</td>\n<td style=\"width: 1.0cm; border-top: none; border-left: none; border-bottom: solid windowtext 1.0pt; border-right: solid windowtext 1.0pt; padding: 0cm 5.4pt 0cm 5.4pt; height: 21.65pt;\" width=\"38\">\n<p style=\"text-align: center; line-height: 200%; margin: 0cm 0cm 0.0001pt; font-size: 10.5pt; font-family: 等线;\" align=\"center\"><span style=\"font-size: 10.0pt; line-height: 200%; font-family: 微软雅黑, sans-serif; color: black;\">5</span></p>\n</td>\n<td style=\"width: 1.0cm; border-top: none; border-left: none; border-bottom: solid windowtext 1.0pt; border-right: solid windowtext 1.0pt; padding: 0cm 5.4pt 0cm 5.4pt; height: 21.65pt;\" width=\"38\">\n<p style=\"text-align: center; line-height: 200%; margin: 0cm 0cm 0.0001pt; font-size: 10.5pt; font-family: 等线;\" align=\"center\"><span style=\"font-size: 10.0pt; line-height: 200%; font-family: 微软雅黑, sans-serif; color: black;\">0</span></p>\n</td>\n<td style=\"width: 42.55pt; border-top: none; border-left: none; border-bottom: solid windowtext 1.0pt; border-right: solid windowtext 1.0pt; padding: 0cm 5.4pt 0cm 5.4pt; height: 21.65pt;\" width=\"57\">\n<p style=\"text-align: center; line-height: 200%; margin: 0cm 0cm 0.0001pt; font-size: 10.5pt; font-family: 等线;\" align=\"center\"><span style=\"font-size: 10.0pt; line-height: 200%; font-family: 微软雅黑, sans-serif; color: black;\">0/25g</span></p>\n</td>\n<td style=\"width: 42.8pt; border-top: none; border-left: none; border-bottom: solid windowtext 1.0pt; border-right: solid windowtext 1.0pt; padding: 0cm 5.4pt 0cm 5.4pt; height: 21.65pt;\" width=\"57\">\n<p style=\"text-align: center; line-height: 200%; margin: 0cm 0cm 0.0001pt; font-size: 10.5pt; font-family: 等线;\" align=\"center\"><span style=\"font-size: 10.0pt; line-height: 200%; font-family: 微软雅黑, sans-serif; color: black;\">-</span></p>\n</td>\n<td style=\"width: 105.55pt; border-top: none; border-left: none; border-bottom: solid windowtext 1.0pt; border-right: solid windowtext 1.0pt; padding: 0cm 5.4pt 0cm 5.4pt; height: 21.65pt;\" width=\"141\">\n<p style=\"line-height: 200%; margin: 0cm 0cm 0.0001pt; font-size: 10.5pt; font-family: 等线; text-align: center;\"><span style=\"font-size: 10.0pt; line-height: 200%; font-family: 微软雅黑, sans-serif; color: black;\">GB4789.4</span></p>\n</td>\n</tr>\n<tr style=\"height: 22.0pt;\">\n<td style=\"width: 49.65pt; border: solid windowtext 1.0pt; border-top: none; padding: 0cm 5.4pt 0cm 5.4pt; height: 22.0pt;\" rowspan=\"2\" width=\"66\">\n<p style=\"line-height: 200%; margin: 0cm 0cm 0.0001pt; font-size: 10.5pt; font-family: 等线; text-align: center;\"><span style=\"font-size: 10.0pt; line-height: 200%; font-family: 微软雅黑, sans-serif; color: black;\">调理牛排</span></p>\n</td>\n<td style=\"width: 120.7pt; border-top: none; border-left: none; border-bottom: solid windowtext 1.0pt; border-right: solid windowtext 1.0pt; padding: 0cm 5.4pt 0cm 5.4pt; height: 22.0pt;\" width=\"161\">\n<p style=\"line-height: 200%; margin: 0cm 0cm 0.0001pt; font-size: 10.5pt; font-family: 等线; text-align: center;\"><span style=\"font-size: 10.0pt; line-height: 200%; font-family: 微软雅黑, sans-serif; color: black;\">金黄色葡萄球菌（CFU/g）</span></p>\n</td>\n<td style=\"width: 1.0cm; border-top: none; border-left: none; border-bottom: solid windowtext 1.0pt; border-right: solid windowtext 1.0pt; padding: 0cm 5.4pt 0cm 5.4pt; height: 22.0pt;\" width=\"38\">\n<p style=\"text-align: center; line-height: 200%; margin: 0cm 0cm 0.0001pt; font-size: 10.5pt; font-family: 等线;\" align=\"center\"><span style=\"font-size: 10.0pt; line-height: 200%; font-family: 微软雅黑, sans-serif; color: black;\">5</span></p>\n</td>\n<td style=\"width: 1.0cm; border-top: none; border-left: none; border-bottom: solid windowtext 1.0pt; border-right: solid windowtext 1.0pt; padding: 0cm 5.4pt 0cm 5.4pt; height: 22.0pt;\" width=\"38\">\n<p style=\"text-align: center; line-height: 200%; margin: 0cm 0cm 0.0001pt; font-size: 10.5pt; font-family: 等线;\" align=\"center\"><span style=\"font-size: 10.0pt; line-height: 200%; font-family: 微软雅黑, sans-serif; color: black;\">1</span></p>\n</td>\n<td style=\"width: 42.55pt; border-top: none; border-left: none; border-bottom: solid windowtext 1.0pt; border-right: solid windowtext 1.0pt; padding: 0cm 5.4pt 0cm 5.4pt; height: 22.0pt;\" width=\"57\">\n<p style=\"text-align: center; line-height: 200%; margin: 0cm 0cm 0.0001pt; font-size: 10.5pt; font-family: 等线;\" align=\"center\"><span style=\"font-size: 10.0pt; line-height: 200%; font-family: 微软雅黑, sans-serif; color: black;\">1000</span></p>\n</td>\n<td style=\"width: 42.8pt; border-top: none; border-left: none; border-bottom: solid windowtext 1.0pt; border-right: solid windowtext 1.0pt; padding: 0cm 5.4pt 0cm 5.4pt; height: 22.0pt;\" width=\"57\">\n<p style=\"text-align: center; line-height: 200%; margin: 0cm 0cm 0.0001pt; font-size: 10.5pt; font-family: 等线;\" align=\"center\"><span style=\"font-size: 10.0pt; line-height: 200%; font-family: 微软雅黑, sans-serif; color: black;\">10000</span></p>\n</td>\n<td style=\"width: 105.55pt; border-top: none; border-left: none; border-bottom: solid windowtext 1.0pt; border-right: solid windowtext 1.0pt; padding: 0cm 5.4pt 0cm 5.4pt; height: 22.0pt;\" width=\"141\">\n<p style=\"line-height: 200%; margin: 0cm 0cm 0.0001pt; font-size: 10.5pt; font-family: 等线; text-align: center;\"><span style=\"font-size: 10.0pt; line-height: 200%; font-family: 微软雅黑, sans-serif; color: black;\">GB4789.10</span><span style=\"font-size: 10.0pt; line-height: 200%; font-family: 微软雅黑, sans-serif; color: black;\">平板计数法</span></p>\n</td>\n</tr>\n<tr style=\"height: 5.25pt;\">\n<td style=\"width: 120.7pt; border-top: none; border-left: none; border-bottom: solid windowtext 1.0pt; border-right: solid windowtext 1.0pt; padding: 0cm 5.4pt 0cm 5.4pt; height: 5.25pt;\" width=\"161\">\n<p style=\"line-height: 200%; margin: 0cm 0cm 0.0001pt; font-size: 10.5pt; font-family: 等线; text-align: center;\"><span style=\"font-size: 10.0pt; line-height: 200%; font-family: 微软雅黑, sans-serif; color: black;\">沙门氏菌（CFU/g）&nbsp;</span></p>\n</td>\n<td style=\"width: 1.0cm; border-top: none; border-left: none; border-bottom: solid windowtext 1.0pt; border-right: solid windowtext 1.0pt; padding: 0cm 5.4pt 0cm 5.4pt; height: 5.25pt;\" width=\"38\">\n<p style=\"text-align: center; line-height: 200%; margin: 0cm 0cm 0.0001pt; font-size: 10.5pt; font-family: 等线;\" align=\"center\"><span style=\"font-size: 10.0pt; line-height: 200%; font-family: 微软雅黑, sans-serif; color: black;\">5</span></p>\n</td>\n<td style=\"width: 1.0cm; border-top: none; border-left: none; border-bottom: solid windowtext 1.0pt; border-right: solid windowtext 1.0pt; padding: 0cm 5.4pt 0cm 5.4pt; height: 5.25pt;\" width=\"38\">\n<p style=\"text-align: center; line-height: 200%; margin: 0cm 0cm 0.0001pt; font-size: 10.5pt; font-family: 等线;\" align=\"center\"><span style=\"font-size: 10.0pt; line-height: 200%; font-family: 微软雅黑, sans-serif; color: black;\">0</span></p>\n</td>\n<td style=\"width: 42.55pt; border-top: none; border-left: none; border-bottom: solid windowtext 1.0pt; border-right: solid windowtext 1.0pt; padding: 0cm 5.4pt 0cm 5.4pt; height: 5.25pt;\" width=\"57\">\n<p style=\"text-align: center; line-height: 200%; margin: 0cm 0cm 0.0001pt; font-size: 10.5pt; font-family: 等线;\" align=\"center\"><span style=\"font-size: 10.0pt; line-height: 200%; font-family: 微软雅黑, sans-serif; color: black;\">0/25g</span></p>\n</td>\n<td style=\"width: 42.8pt; border-top: none; border-left: none; border-bottom: solid windowtext 1.0pt; border-right: solid windowtext 1.0pt; padding: 0cm 5.4pt 0cm 5.4pt; height: 5.25pt;\" width=\"57\">\n<p style=\"text-align: center; line-height: 200%; margin: 0cm 0cm 0.0001pt; font-size: 10.5pt; font-family: 等线;\" align=\"center\"><span style=\"font-size: 10.0pt; line-height: 200%; font-family: 微软雅黑, sans-serif; color: black;\">-</span></p>\n</td>\n<td style=\"width: 105.55pt; border-top: none; border-left: none; border-bottom: solid windowtext 1.0pt; border-right: solid windowtext 1.0pt; padding: 0cm 5.4pt 0cm 5.4pt; height: 5.25pt;\" width=\"141\">\n<p style=\"line-height: 200%; margin: 0cm 0cm 0.0001pt; font-size: 10.5pt; font-family: 等线; text-align: center;\"><span style=\"font-size: 10.0pt; line-height: 200%; font-family: 微软雅黑, sans-serif; color: black;\">GB4789.4</span></p>\n</td>\n</tr>\n</tbody>\n</table>\n</div>\n<p style=\"text-indent: 21pt; line-height: 200%; margin: 0cm 0cm 0.0001pt; text-align: justify; font-size: 10.5pt; font-family: 等线;\"><span style=\"font-size: 10.0pt; line-height: 200%; font-family: 微软雅黑, sans-serif; color: black;\">4</span><span style=\"font-size: 10.0pt; line-height: 200%; font-family: 微软雅黑, sans-serif; color: black;\">、食品添加剂</span></p>\n<p style=\"text-indent: 21pt; line-height: 200%; margin: 0cm 0cm 0.0001pt; text-align: justify; font-size: 10.5pt; font-family: 等线;\"><span style=\"font-size: 10.0pt; line-height: 200%; font-family: 微软雅黑, sans-serif; color: black;\">食品添加剂使用应符合GB 2760的规定。</span></p>\n<p style=\"text-indent: 21pt; line-height: 200%; margin: 0cm 0cm 0.0001pt; text-align: justify; font-size: 10.5pt; font-family: 等线;\"><strong><span style=\"font-size: 10.0pt; line-height: 200%; font-family: 微软雅黑, sans-serif; color: black;\">（四）净含量</span></strong></p>\n<p style=\"text-indent: 21pt; line-height: 200%; margin: 0cm 0cm 0.0001pt; text-align: justify; font-size: 10.5pt; font-family: 等线;\"><span style=\"font-size: 10.0pt; line-height: 200%; font-family: 微软雅黑, sans-serif; color: black;\">净含量应符合《定量包装商品计量监督管理办法》的有关规定。</span></p>\n<p style=\"text-align: center; line-height: 200%; margin: 0cm 0cm 0.0001pt; font-size: 10.5pt; font-family: 等线;\" align=\"center\"><strong><span style=\"font-size: 10.0pt; line-height: 200%; font-family: 微软雅黑, sans-serif; color: black;\">&nbsp; &nbsp; &nbsp; &nbsp; &nbsp; &nbsp; &nbsp; &nbsp; &nbsp; &nbsp; &nbsp; 第八章 牛排商品命名要求</span></strong></p>\n<p style=\"text-indent: 21pt; line-height: 200%; margin: 0cm 0cm 0.0001pt; text-align: justify; font-size: 10.5pt; font-family: 等线;\"><strong><span style=\"font-size: 10.0pt; line-height: 200%; font-family: 微软雅黑, sans-serif; color: black;\">（一）原切牛排命名规则</span></strong></p>\n<p style=\"text-indent: 21pt; line-height: 200%; margin: 0cm 0cm 0.0001pt; text-align: justify; font-size: 10.5pt; font-family: 等线;\"><span style=\"font-size: 10.0pt; line-height: 200%; font-family: 微软雅黑, sans-serif; color: black;\">原切牛排，一般命名为&rdquo; 品牌名称+产地（国产/xx国进口/新疆产/国产内蒙等形式）/饲养方式（养殖天数）/牛品种/商品等级+原切+部位+厚切/认证宣称+（儿童/家庭组合/套餐/礼盒）牛排+商品净含量/规格（明确具体片数，不同部位组合分别标注）+赠品/配料+状态（冷冻/熟冻/鲜活/冷藏/常温）&rdquo; ，如&ldquo;牛本家 澳洲进口谷饲450天和牛M9原切西冷厚切2.5cm儿童牛排250g （2片） 冷冻&rdquo;。</span></p>\n<p style=\"text-indent: 21pt; line-height: 200%; margin: 0cm 0cm 0.0001pt; text-align: justify; font-size: 10.5pt; font-family: 等线;\"><strong><span style=\"font-size: 10.0pt; line-height: 200%; font-family: 微软雅黑, sans-serif; color: black;\">（二）调理牛排命名规则</span></strong></p>\n<p style=\"text-indent: 21pt; line-height: 200%; margin: 0cm 0cm 0.0001pt; text-align: justify; font-size: 10.5pt; font-family: 等线;\"><span style=\"font-size: 10.0pt; line-height: 200%; font-family: 微软雅黑, sans-serif; color: black;\">1</span><span style=\"font-size: 10.0pt; line-height: 200%; font-family: 微软雅黑, sans-serif; color: black;\">、静腌调理牛排，一般命名为&ldquo;品牌名称+产地（国产/xx国进口/新疆产/国产内蒙等形式）/饲养方式（养殖天数）/牛品种/商品等级+静腌调理+口味+部位+厚切/认证宣称+（儿童/家庭组合/套餐/礼盒）牛排+商品净含量/规格（明确具体片数，组合分别标注）+赠品/配料+状态（冷冻/熟冻/鲜活/冷藏/常温）&rdquo; ，如&ldquo;元盛 国产静腌调理美式黑椒家庭组合牛排1.6kg（10片）内含酱包和牛牛油 冷冻&rdquo;。</span></p>\n<p style=\"text-indent: 21pt; line-height: 200%; margin: 0cm 0cm 0.0001pt; text-align: justify; font-size: 10.5pt; font-family: 等线;\"><span style=\"font-size: 10.0pt; line-height: 200%; font-family: 微软雅黑, sans-serif; color: black;\">2</span><span style=\"font-size: 10.0pt; line-height: 200%; font-family: 微软雅黑, sans-serif; color: black;\">、整切调理牛排，一般命名为&ldquo;品牌名称+产地（国产/xx国进口/新疆产/国产内蒙等形式）/饲养方式（养殖天数）/牛品种+整切调理+口味+部位+厚切/认证宣称+（儿童/家庭组合/套餐/礼盒）牛排+商品净含量/规格（明确具体片数，组合分别标注）+赠品/配料+状态（冷冻/熟冻/鲜活/冷藏/常温）&rdquo; ，如&ldquo;恒都 国产整切调理西冷+眼肉套餐牛排 1.5kg/套（西冷5片+眼肉5片）送料包 冷冻&rdquo;。</span></p>\n<p style=\"text-indent: 21pt; line-height: 200%; margin: 0cm 0cm 0.0001pt; text-align: justify; font-size: 10.5pt; font-family: 等线;\"><span style=\"font-size: 10.0pt; line-height: 200%; font-family: 微软雅黑, sans-serif; color: black;\">3</span><span style=\"font-size: 10.0pt; line-height: 200%; font-family: 微软雅黑, sans-serif; color: black;\">、加工调理牛排，一般命名为&ldquo;品牌名称 +产地（国产/xx国进口/新疆产/国产内蒙等形式）+加工调理+口味+部位+厚切/认证宣称+（家庭组合/套餐/礼盒）牛排+商品净含量/规格（明确具体片数，组合分别标注）+赠品/配料+状态（冷冻/熟冻/鲜活/冷藏/常温） ，如&ldquo;伊赛 国产加工调理菲力套餐牛排 1.2kg/套(12片)&nbsp; 冷冻&rdquo;。</span></p>\n<p style=\"text-indent: 21pt; line-height: 200%; margin: 0cm 0cm 0.0001pt; text-align: justify; font-size: 10.5pt; font-family: 等线;\"><strong><span style=\"font-size: 10.0pt; line-height: 200%; font-family: 微软雅黑, sans-serif; color: black;\">（三）其他说明</span></strong></p>\n<p style=\"text-indent: 21pt; line-height: 200%; margin: 0cm 0cm 0.0001pt; text-align: justify; font-size: 10.5pt; font-family: 等线;\"><span style=\"font-size: 10.0pt; line-height: 200%; font-family: 微软雅黑, sans-serif; color: black;\">1</span><span style=\"font-size: 10.0pt; line-height: 200%; font-family: 微软雅黑, sans-serif; color: black;\">、命名内容中包含商品等级，需提供等级证明并在页面清晰展示。</span></p>\n<p style=\"text-indent: 21pt; line-height: 200%; margin: 0cm 0cm 0.0001pt; text-align: justify; font-size: 10.5pt; font-family: 等线;\"><span style=\"font-size: 10.0pt; line-height: 200%; font-family: 微软雅黑, sans-serif; color: black;\">2</span><span style=\"font-size: 10.0pt; line-height: 200%; font-family: 微软雅黑, sans-serif; color: black;\">、命名内容中包含认证宣称，需提供相关证书并在页面清晰展示，如涉及有机认证等。</span></p>\n<p style=\"text-indent: 21pt; line-height: 200%; margin: 0cm 0cm 0.0001pt; text-align: justify; font-size: 10.5pt; font-family: 等线;\"><span style=\"font-size: 10.0pt; line-height: 200%; font-family: 微软雅黑, sans-serif; color: black;\">3</span><span style=\"font-size: 10.0pt; line-height: 200%; font-family: 微软雅黑, sans-serif; color: black;\">、命名内容中包含厚切，厚度需＞2cm，且厚度区间值&le;0.5cm ，示例：合规 2cm-2.5cm，2.5cm-3cm；不合规 1.5cm-3cm。</span></p>\n<p style=\"text-indent: 21pt; line-height: 200%; margin: 0cm 0cm 0.0001pt; text-align: justify; font-size: 10.5pt; font-family: 等线;\"><span style=\"font-size: 10.0pt; line-height: 200%; font-family: 微软雅黑, sans-serif; color: black;\">4</span><span style=\"font-size: 10.0pt; line-height: 200%; font-family: 微软雅黑, sans-serif; color: black;\">、（一）、（二）标题不得随意变更顺序，命名内容中&ldquo;饲养方式（养殖天数）/牛品种/商品等级&rdquo;、&ldquo;口味&rdquo;、&ldquo;部位（除原切牛排）&rdquo;、&ldquo;厚切/认证宣称&rdquo;、&ldquo;儿童/家庭组合/套餐/礼盒&rdquo;、&ldquo;赠品/配料&rdquo;为非必须包含内容，商家可根据商品实际情况进行调整，其余均为必填内容。非对应部位商品，不得使用部位命名。</span></p>\n<p style=\"text-indent: 21pt; line-height: 200%; margin: 0cm 0cm 0.0001pt; text-align: justify; font-size: 10.5pt; font-family: 等线;\"><span style=\"font-size: 10.0pt; line-height: 200%; font-family: 微软雅黑, sans-serif; color: black;\">5</span><span style=\"font-size: 10.0pt; line-height: 200%; font-family: 微软雅黑, sans-serif; color: black;\">、不同类别商品组合销售的，以&ldquo;原切&rdquo;和&ldquo;调理&rdquo;两个大类进行命名，原切商品中附加调理商品，不得以原切商品命名。如&ldquo;整切调理+加工调理&rdquo;组合售卖的商品，应统一命名为&ldquo;调理&rdquo;，不得以&ldquo;整切调理&rdquo;命名全部商品。</span></p>\n<p style=\"text-indent: 21pt; line-height: 200%; margin: 0cm 0cm 0.0001pt; text-align: justify; font-size: 10.5pt; font-family: 等线;\"><span style=\"font-size: 10.0pt; line-height: 200%; font-family: 微软雅黑, sans-serif; color: black;\">6</span><span style=\"font-size: 10.0pt; line-height: 200%; font-family: 微软雅黑, sans-serif; color: black;\">、静腌调理牛排、整切调理牛排、加工调理牛排，命名内容中，不得出现&ldquo;原切&rdquo;、&ldquo;原肉&rdquo;、&ldquo;原肉整切&rdquo;、&ldquo;整切原肉&rdquo;等易产生歧义的字样，也不得出现&ldquo;非原切&rdquo;之类的宣传。</span></p>\n<p style=\"text-indent: 21pt; line-height: 200%; margin: 0cm 0cm 0.0001pt; text-align: justify; font-size: 10.5pt; font-family: 等线;\"><span style=\"font-size: 10.0pt; line-height: 200%; font-family: 微软雅黑, sans-serif; color: black;\">7</span><span style=\"font-size: 10.0pt; line-height: 200%; font-family: 微软雅黑, sans-serif; color: black;\">、非本标准中规定类别的商品，加工原料使用肉糜、碎肉成型压制的商品，不得以&ldquo;牛排&rdquo;命名。</span></p>\n<p style=\"text-indent: 21pt; line-height: 200%; margin: 0cm 0cm 0.0001pt; text-align: justify; font-size: 10.5pt; font-family: 等线;\">&nbsp;</p>\n<p style=\"text-align: center; line-height: 200%; margin: 0cm 0cm 0.0001pt; font-size: 10.5pt; font-family: 等线;\" align=\"center\"><strong><span style=\"font-size: 10.0pt; line-height: 200%; font-family: 微软雅黑, sans-serif; color: black;\">&nbsp; &nbsp; &nbsp; &nbsp; &nbsp; &nbsp; &nbsp; &nbsp; &nbsp; &nbsp; &nbsp; &nbsp; &nbsp; 第九章 牛排商品商详信息要求</span></strong></p>\n<p style=\"text-indent: 20pt; line-height: 200%; margin: 0cm 0cm 0.0001pt; text-align: justify; font-size: 10.5pt; font-family: 等线;\"><span style=\"font-size: 10.0pt; line-height: 200%; font-family: 微软雅黑, sans-serif; color: black;\">&nbsp; 商详页面需展示商品全部配料信息，且原切牛排配料仅有牛肉。</span></p>\n<p style=\"text-align: center; line-height: 200%; margin: 0cm 0cm 0.0001pt; font-size: 10.5pt; font-family: 等线;\" align=\"center\"><strong><span style=\"font-size: 10.0pt; line-height: 200%; font-family: 微软雅黑, sans-serif; color: black;\">&nbsp; &nbsp; &nbsp; &nbsp;第十章 检验报告</span></strong></p>\n<p style=\"text-indent: 21pt; line-height: 200%; margin: 0cm 0cm 0.0001pt; text-align: justify; font-size: 10.5pt; font-family: 等线;\"><span style=\"font-size: 10.0pt; line-height: 200%; font-family: 微软雅黑, sans-serif; color: black;\"><strong>（一）</strong>各生产单位应按照执行标准进行出厂检验报告和型式检验报告的提供，也应满足本标准相关第七章要求。</span></p>\n<p style=\"text-indent: 21pt; line-height: 200%; margin: 0cm 0cm 0.0001pt; text-align: justify; font-size: 10.5pt; font-family: 等线;\"><span style=\"font-size: 10.0pt; line-height: 200%; font-family: 微软雅黑, sans-serif; color: black;\"><strong>（二）</strong>本标准中第七章均作为京东平台抽检牛排商品内控检测项目。</span></p>\n<p style=\"text-align: center; line-height: 200%; margin: 0cm 0cm 0.0001pt; font-size: 10.5pt; font-family: 等线;\" align=\"center\"><strong><span style=\"font-size: 10.0pt; line-height: 200%; font-family: 微软雅黑, sans-serif; color: black;\">&nbsp; &nbsp; &nbsp;第十一章 标签</span></strong></p>\n<p style=\"text-indent: 21pt; line-height: 200%; margin: 0cm 0cm 0.0001pt; text-align: justify; font-size: 10.5pt; font-family: 等线;\"><span style=\"font-size: 10.0pt; line-height: 200%; font-family: 微软雅黑, sans-serif; color: black;\"><strong>（一）</strong>商品标签应符合GB7718、GB28050、《食品标识管理规定》及其他相关规定的要求。</span></p>\n<p style=\"text-indent: 21pt; line-height: 200%; margin: 0cm 0cm 0.0001pt; text-align: justify; font-size: 10.5pt; font-family: 等线;\"><span style=\"font-size: 10.0pt; line-height: 200%; font-family: 微软雅黑, sans-serif; color: black;\"><strong>（二）</strong>调理牛排标签应符合SB/T10379《速冻调制食品》的有关规定，且标签中不得出现&ldquo;原切&rdquo;字样。</span></p>\n<p style=\"text-indent: 21pt; line-height: 200%; margin: 0cm 0cm 0.0001pt; text-align: justify; font-size: 10.5pt; font-family: 等线;\">&nbsp;</p>\n<p style=\"text-align: center; line-height: 200%; margin: 0cm 0cm 0.0001pt; font-size: 10.5pt; font-family: 等线;\" align=\"center\"><strong><span style=\"font-size: 10.0pt; line-height: 200%; font-family: 微软雅黑, sans-serif; color: black;\">&nbsp; &nbsp; &nbsp; &nbsp; &nbsp; &nbsp; 第十二章 违规处理</span></strong></p>\n<p style=\"text-indent: 21pt; line-height: 200%; margin: 0cm 0cm 0.0001pt; text-align: justify; font-size: 10.5pt; font-family: 等线;\"><span style=\"font-size: 10.0pt; line-height: 200%; font-family: 微软雅黑, sans-serif; color: black;\"><strong>（一）</strong>在京东开放平台经营牛排类商品的商家应遵守该质量标准要求，若经京东或委托的第三方抽检出现商品不符合质量标准要求，京东将依据<span style=\"font-size: 10.0pt; font-family: 微软雅黑, sans-serif;\"><a style=\"color: blue; text-decoration: underline;\" href=\"https://rule.jd.com/rule/ruleDetail.action?ruleId=2754&amp;type=0&amp;btype=1\" target=\"_blank\" rel=\"noopener\">《京东开放平台商家违规管理总则》</a></span> </span><span style=\"font-size: 10.0pt; line-height: 200%; font-family: 微软雅黑, sans-serif; color: black;\">的商品质量不合格情形进行处理，对于发现的质量不合格商品予以违规商品下架等违规处理。</span></p>\n<p style=\"text-indent: 21pt; line-height: 200%; margin: 0cm 0cm 0.0001pt; text-align: justify; font-size: 10.5pt; font-family: 等线;\"><span style=\"font-size: 10.0pt; line-height: 200%; font-family: 微软雅黑, sans-serif; color: black;\"><strong>（二）</strong>若商家发布的牛排商品标题不符合本规则第8章&ldquo;牛排商品命名要求&rdquo;和 第9章&ldquo;牛排商品商详信息要求&rdquo;，京东将依据<span style=\"font-size: 10.0pt; font-family: 微软雅黑, sans-serif;\"><a style=\"color: blue; text-decoration: underline;\" href=\"https://rule.jd.com/rule/ruleDetail.action?ruleId=2754&amp;type=0&amp;btype=1\" target=\"_blank\" rel=\"noopener\">《京东开放平台商家违规管理总则》</a></span> </span><span style=\"font-size: 10.0pt; line-height: 200%; font-family: 微软雅黑, sans-serif; color: black;\">的不当发布商品信息情形进行处理，对于发现的违规商品按情节轻重程度予以警告、违规商品下架<span style=\"font-size: 10pt; line-height: 200%; font-family: 微软雅黑, sans-serif; color: black;\">等违规处理</span>。</span></p>\n<p style=\"text-indent: 21pt; line-height: 200%; margin: 0cm 0cm 0.0001pt; text-align: justify; font-size: 10.5pt; font-family: 等线;\"><span style=\"font-size: 10.0pt; line-height: 200%; font-family: 微软雅黑, sans-serif; color: black;\"><strong>（三）</strong>若商家虚假发布牛排商品信息，牛排品牌名称、产地、饲养方式、牛品种、商品等级、原料、部位、厚切、认证宣称、商品净含量/规格与商品实际内容不相符，京东将依据<span style=\"font-size: 10.0pt; font-family: 微软雅黑, sans-serif;\"><a style=\"color: blue; text-decoration: underline;\" href=\"https://rule.jd.com/rule/ruleDetail.action?ruleId=2754&amp;type=0&amp;btype=1\" target=\"_blank\" rel=\"noopener\">《京东开放平台商家违规管理总则》</a></span> </span><span style=\"font-size: 10.0pt; line-height: 200%; font-family: 微软雅黑, sans-serif; color: black;\">的虚假宣传情形进行处理，对于发现的违规商品予以下架<span style=\"font-size: 10pt; line-height: 200%; font-family: 微软雅黑, sans-serif; color: black;\">等违规处理</span>。</span></p>\n<p style=\"text-align: center; line-height: 200%; margin: 0cm 0cm 0.0001pt; font-size: 10.5pt; font-family: 等线;\" align=\"center\"><strong><span style=\"font-size: 10.0pt; line-height: 200%; font-family: 微软雅黑, sans-serif; color: black;\">&nbsp; &nbsp; &nbsp; 第十三章 附则</span></strong></p>\n<p style=\"text-indent: 21pt; line-height: 200%; margin: 0cm 0cm 0.0001pt; text-align: justify; font-size: 10.5pt; font-family: 等线;\"><span style=\"font-size: 10.0pt; line-height: 200%; font-family: 微软雅黑, sans-serif; color: black;\"><strong>（一）</strong>京东开放平台商家的行为，发生在本管理规则生效之日以前的，适用当时的规则。发生在本管理规则生效之日以后的，适用本规则。</span></p>\n<p style=\"text-indent: 21pt; line-height: 200%; margin: 0cm 0cm 0.0001pt; text-align: justify; font-size: 10.5pt; font-family: 等线;\"><span style=\"font-size: 10.0pt; line-height: 200%; font-family: 微软雅黑, sans-serif; color: black;\"><strong>（二）</strong>京东可根据平台运营情况随时调整本管理规则并以&ldquo;京东开放平台&rdquo;公告的形式向商家公示；商家入驻京东即表示接受京东其后不时调整、颁布的管理规则。</span></p>\n<p style=\"text-indent: 21pt; line-height: 200%; margin: 0cm 0cm 0.0001pt; text-align: justify; font-size: 10.5pt; font-family: 等线;\"><span style=\"font-size: 10.0pt; line-height: 200%; font-family: 微软雅黑, sans-serif; color: black;\"><strong>（三）</strong>商家应遵守国家法律、行政法规、部门规章等规范性文件。对任何涉嫌违反国家法律、行政法规、部门规章等规范性文件的行为，本规则已有规定的，适用于本规则。本规则尚无规定的，京东有权酌情处理，但京东对商家的处理不免除其应承担的法律责任。商家在京东的任何行为，应同时遵守与京东及其关联公司签订的各项协议；如有违约即视为对本规则的违反。</span></p>\n<p style=\"text-indent: 21pt; line-height: 200%; margin: 0cm 0cm 0.0001pt; text-align: justify; font-size: 10.5pt; font-family: 等线;\"><span style=\"font-size: 10.0pt; line-height: 200%; font-family: 微软雅黑, sans-serif; color: black;\"><strong>（四）</strong>该规则于2020年6月1日首次发布，于2022年5月10日修订，于2022年5月17日生效。</span></p>",
    "selectCategoryId": [
      "578",
      "579"
    ],
    "categoryIdPath": "578,579",
    "labelIds": "1",
    "top": "0",
    "jfsContentUrl": "//storage.jd.com/karmavender/file/scene/20250324/77ef8daa765b4be48e06b37ca24296ce.txt",
    "pdfFileUrl": "//storage.jd.com/karmavender/file/pdf/20220510/bc2dff6576fe4b3fa7114d2605bd9626.pdf",
    "showCollect": false,
    "hideCollectButton": true,
    "id": "584633040848949248",
    "summary": "京东开放平台生鲜牛排类商品管理规范",
    "uv": "1",
    "solvePin": "张莹莹",
    "changeReason": "",
    "preRuleId": "669790242710097920",
    "activeTime": 1652716800000,
    "multiCategoryId": "",
    "solveDept": " 京东集团-京东零售-大商超全渠道事业群-经营提升部-生鲜运营提升部-品质提升组",
    "updateUser": "zhuchaoyang1",
    "updateTime": 1780599603443,
    "keyWord": "京东开放平台生鲜牛排类商品管理规范",
    "allLabelIds": "5392,5364,5069,5391",
    "preRuleTitle": "京东开放平台LOC商品管理规则",
    "createTime": 1590993778000,
    "followRuleTitle": "京东开放平台网络食品交易管理制度",
    "createUser": "zuoningning5",
    "businessType": 1,
    "categoryId": "579",
    "status": 1
  }
}