{
  "rule_id": "907471114710683648",
  "scope": [
    "enterprise"
  ],
  "source_url": "https://learn-jdm.jd.com/knowledge/rule/detail?ruleId=907471114710683648",
  "search": {
    "title": "京东开放平台健康服务类目资质标准",
    "summary": "京东开放平台健康服务类目资质标准",
    "created": "2022-11-09",
    "modified": "2024-11-19",
    "url": "https://rule.jd.com/rule/ruleDetail.action?ruleId=907471114710683648&type=0&btype=1"
  },
  "detail": {
    "pv": "2",
    "endLabelIds": "",
    "endLabelNames": "",
    "title": "京东开放平台健康服务类目资质标准",
    "followRuleId": "907468120992649216",
    "content": "<table class=\"MsoNormalTable\" style=\"width: 100.0%; background: white; border-collapse: collapse; border: none;\" border=\"1\" width=\"100%\" cellspacing=\"0\" cellpadding=\"0\">\n<tbody>\n<tr>\n<td style=\"width: 56.9pt; border: solid windowtext 1.0pt; background: #C00000; padding: 0cm 5.4pt 0cm 5.4pt;\" width=\"76\">\n<p style=\"margin: 0cm 0cm 0.0001pt -6pt; text-align: center; line-height: 200%; font-size: 10.5pt; font-family: 等线;\" align=\"center\"><strong><span style=\"font-size: 10.0pt; line-height: 200%; font-family: 微软雅黑, sans-serif; color: white;\">一级类目</span></strong></p>\n</td>\n<td style=\"width: 64.0pt; border: solid windowtext 1.0pt; border-left: none; background: #C00000; padding: 0cm 5.4pt 0cm 5.4pt;\" width=\"85\">\n<p style=\"text-align: center; line-height: 200%; margin: 0cm 0cm 0.0001pt; font-size: 10.5pt; font-family: 等线;\" align=\"center\"><strong><span style=\"font-size: 10.0pt; line-height: 200%; font-family: 微软雅黑, sans-serif; color: white;\">二级类目</span></strong></p>\n</td>\n<td style=\"width: 176.3pt; border: solid windowtext 1.0pt; border-left: none; background: #C00000; padding: 0cm 5.4pt 0cm 5.4pt;\" width=\"41\">\n<p style=\"text-align: center; line-height: 200%; margin: 0cm 0cm 0.0001pt; font-size: 10.5pt; font-family: 等线;\" align=\"center\"><strong><span style=\"font-size: 10.0pt; line-height: 200%; font-family: 微软雅黑, sans-serif; color: white;\">行业资质</span></strong></p>\n</td>\n<td style=\"width: 399.7pt; border: solid windowtext 1.0pt; border-left: none; background: #C00000; padding: 0cm 5.4pt 0cm 5.4pt;\" colspan=\"2\" width=\"328\">\n<p style=\"text-align: center; line-height: 200%; margin: 0cm 0cm 0.0001pt; font-size: 10.5pt; font-family: 等线;\" align=\"center\"><strong><span style=\"font-size: 10.0pt; line-height: 200%; font-family: 微软雅黑, sans-serif; color: white;\">特殊资质及要求</span></strong></p>\n</td>\n</tr>\n<tr>\n<td style=\"width: 56.9pt; border: solid windowtext 1.0pt; border-top: none; padding: 0cm 5.4pt 0cm 5.4pt;\" rowspan=\"13\" nowrap=\"nowrap\" width=\"76\">\n<p style=\"margin: 0cm 0cm 0.0001pt -6pt; text-align: center; line-height: 200%; font-size: 10.5pt; font-family: 等线;\" align=\"center\"><span style=\"font-size: 10.0pt; line-height: 200%; font-family: 微软雅黑, sans-serif; color: black;\">健康服务</span></p>\n</td>\n<td style=\"width: 64.0pt; border-top: none; border-left: none; border-bottom: solid windowtext 1.0pt; border-right: solid windowtext 1.0pt; padding: 0cm 5.4pt 0cm 5.4pt;\" nowrap=\"nowrap\" width=\"85\">\n<p style=\"text-align: center; line-height: 200%; margin: 0cm 0cm 0.0001pt; font-size: 10.5pt; font-family: 等线;\" align=\"center\"><span style=\"font-size: 10.0pt; line-height: 200%; font-family: 微软雅黑, sans-serif; color: black;\">基因检测</span></p>\n</td>\n<td style=\"width: 176.3pt; border-top: none; border-left: none; border-bottom: solid windowtext 1.0pt; border-right: solid windowtext 1.0pt; padding: 0cm 5.4pt 0cm 5.4pt;\" width=\"41\">\n<p style=\"text-align: center; line-height: 200%; margin: 0cm 0cm 0.0001pt; font-size: 10.5pt; font-family: 等线;\" align=\"center\"><span style=\"font-size: 10.0pt; line-height: 200%; font-family: 微软雅黑, sans-serif; color: black;\">《医疗机构执业许可证》</span></p>\n</td>\n<td style=\"width: 225.25pt; border-top: none; border-left: none; border-bottom: solid windowtext 1.0pt; border-right: solid windowtext 1.0pt; padding: 0cm 5.4pt 0cm 5.4pt;\" width=\"300\">\n<p style=\"text-align: center; line-height: 200%; margin: 0cm 0cm 0.0001pt; font-size: 10.5pt; font-family: 等线;\" align=\"center\"><span style=\"font-size: 10.0pt; line-height: 200%; font-family: 微软雅黑, sans-serif; color: black;\">/</span></p>\n</td>\n<td style=\"width: 174.45pt; border-top: none; border-left: none; border-bottom: solid windowtext 1.0pt; border-right: solid windowtext 1.0pt; padding: 0cm 0cm 0cm 0cm;\" rowspan=\"13\" width=\"28\">\n<p style=\"line-height: 200%; margin: 0cm 0cm 0.0001pt; text-align: justify; font-size: 10.5pt; font-family: 等线;\"><span style=\"font-size: 10.0pt; line-height: 200%; font-family: 微软雅黑, sans-serif; color: black;\">1. TM</span><span style=\"font-size: 10.0pt; line-height: 200%; font-family: 微软雅黑, sans-serif; color: black;\">标申请时间至入驻审核时间必须大于3个月，TM标有效期请填写申请日期+2年后的日期，R标有效期按商标注册证有效日期填写。</span></p>\n<p style=\"line-height: 200%; margin: 0cm 0cm 0.0001pt; text-align: justify; font-size: 10.5pt; font-family: 等线;\"><span style=\"font-size: 10.0pt; line-height: 200%; font-family: 微软雅黑, sans-serif; color: black;\">2. </span><span style=\"font-size: 10.0pt; line-height: 200%; font-family: 微软雅黑, sans-serif; color: black;\">专卖店、专营店需有3级以内（包括3级）的完整授权链路。</span></p>\n</td>\n</tr>\n<tr>\n<td style=\"width: 64.0pt; border-top: none; border-left: none; border-bottom: solid windowtext 1.0pt; border-right: solid windowtext 1.0pt; padding: 0cm 5.4pt 0cm 5.4pt;\" nowrap=\"nowrap\" width=\"85\">\n<p style=\"text-align: center; line-height: 200%; margin: 0cm 0cm 0.0001pt; font-size: 10.5pt; font-family: 等线;\" align=\"center\"><span style=\"font-size: 10.0pt; line-height: 200%; font-family: 微软雅黑, sans-serif; color: black;\">健康体检</span></p>\n</td>\n<td style=\"width: 176.3pt; border-top: none; border-left: none; border-bottom: solid windowtext 1.0pt; border-right: solid windowtext 1.0pt; padding: 0cm 5.4pt 0cm 5.4pt;\" width=\"41\">\n<p style=\"text-align: center; line-height: 200%; margin: 0cm 0cm 0.0001pt; font-size: 10.5pt; font-family: 等线;\" align=\"center\"><span style=\"font-size: 10.0pt; line-height: 200%; font-family: 微软雅黑, sans-serif; color: black;\">《医疗机构执业许可证》</span></p>\n</td>\n<td style=\"width: 225.25pt; border-top: none; border-left: none; border-bottom: solid windowtext 1.0pt; border-right: solid windowtext 1.0pt; padding: 0cm 5.4pt 0cm 5.4pt;\" width=\"300\">\n<p style=\"text-align: center; line-height: 200%; margin: 0cm 0cm 0.0001pt; font-size: 10.5pt; font-family: 等线;\" align=\"center\"><span style=\"font-size: 10.0pt; line-height: 200%; font-family: 微软雅黑, sans-serif;\">公立机构可以查询公示网站截图</span></p>\n</td>\n</tr>\n<tr>\n<td style=\"width: 64.0pt; border-top: none; border-left: none; border-bottom: solid windowtext 1.0pt; border-right: solid windowtext 1.0pt; padding: 0cm 5.4pt 0cm 5.4pt;\" nowrap=\"nowrap\" width=\"85\">\n<p style=\"text-align: center; line-height: 200%; margin: 0cm 0cm 0.0001pt; font-size: 10.5pt; font-family: 等线;\" align=\"center\"><span style=\"font-size: 10.0pt; line-height: 200%; font-family: 微软雅黑, sans-serif; color: black;\">健康管理</span></p>\n</td>\n<td style=\"width: 176.3pt; border-top: none; border-left: none; border-bottom: solid windowtext 1.0pt; border-right: solid windowtext 1.0pt; padding: 0cm 5.4pt 0cm 5.4pt;\" width=\"41\">\n<p style=\"text-align: center; line-height: 200%; margin: 0cm 0cm 0.0001pt; font-size: 10.5pt; font-family: 等线;\" align=\"center\"><span style=\"font-size: 10.0pt; line-height: 200%; font-family: 微软雅黑, sans-serif; color: black;\">/</span></p>\n</td>\n<td style=\"width: 225.25pt; border-top: none; border-left: none; border-bottom: solid windowtext 1.0pt; border-right: solid windowtext 1.0pt; padding: 0cm 5.4pt 0cm 5.4pt;\" nowrap=\"nowrap\" width=\"300\">\n<p style=\"text-align: center; line-height: 200%; margin: 0cm 0cm 0.0001pt; font-size: 10.5pt; font-family: 等线;\" align=\"center\"><span style=\"font-size: 10.0pt; line-height: 200%; font-family: 微软雅黑, sans-serif; color: black;\">经营范围：不含许可经营项目</span></p>\n</td>\n</tr>\n<tr>\n<td style=\"width: 64.0pt; border-top: none; border-left: none; border-bottom: solid windowtext 1.0pt; border-right: solid windowtext 1.0pt; padding: 0cm 5.4pt 0cm 5.4pt;\" nowrap=\"nowrap\" width=\"85\">\n<p style=\"text-align: center; line-height: 200%; margin: 0cm 0cm 0.0001pt; font-size: 10.5pt; font-family: 等线;\" align=\"center\"><span style=\"font-size: 10.0pt; line-height: 200%; font-family: 微软雅黑, sans-serif; color: black;\">营养康复</span></p>\n</td>\n<td style=\"width: 176.3pt; border-top: none; border-left: none; border-bottom: solid windowtext 1.0pt; border-right: solid windowtext 1.0pt; padding: 0cm 5.4pt 0cm 5.4pt;\" width=\"41\">\n<p style=\"text-align: center; line-height: 200%; margin: 0cm 0cm 0.0001pt; font-size: 10.5pt; font-family: 等线;\" align=\"center\"><span style=\"font-size: 10.0pt; line-height: 200%; font-family: 微软雅黑, sans-serif; color: black;\">/</span></p>\n</td>\n<td style=\"width: 225.25pt; border-top: none; border-left: none; border-bottom: solid windowtext 1.0pt; border-right: solid windowtext 1.0pt; padding: 0cm 5.4pt 0cm 5.4pt;\" width=\"300\">\n<p style=\"text-align: center; line-height: 200%; margin: 0cm 0cm 0.0001pt; font-size: 10.5pt; font-family: 等线;\" align=\"center\"><span style=\"font-size: 10.0pt; line-height: 200%; font-family: 微软雅黑, sans-serif; color: black;\">经营范围：不含许可经营项目</span></p>\n</td>\n</tr>\n<tr>\n<td style=\"width: 64.0pt; border-top: none; border-left: none; border-bottom: solid windowtext 1.0pt; border-right: solid windowtext 1.0pt; padding: 0cm 5.4pt 0cm 5.4pt;\" nowrap=\"nowrap\" width=\"85\">\n<p style=\"text-align: center; line-height: 200%; margin: 0cm 0cm 0.0001pt; font-size: 10.5pt; font-family: 等线;\" align=\"center\"><span style=\"font-size: 10.0pt; line-height: 200%; font-family: 微软雅黑, sans-serif; color: black;\">口腔齿科</span></p>\n</td>\n<td style=\"width: 176.3pt; border-top: none; border-left: none; border-bottom: solid windowtext 1.0pt; border-right: solid windowtext 1.0pt; padding: 0cm 5.4pt 0cm 5.4pt;\" width=\"41\">\n<p style=\"text-align: center; line-height: 200%; margin: 0cm 0cm 0.0001pt; font-size: 10.5pt; font-family: 等线;\" align=\"center\"><span style=\"font-size: 10.0pt; line-height: 200%; font-family: 微软雅黑, sans-serif; color: black;\">《医疗机构执业许可证》</span></p>\n</td>\n<td style=\"width: 225.25pt; border-top: none; border-left: none; border-bottom: solid windowtext 1.0pt; border-right: solid windowtext 1.0pt; padding: 0cm 5.4pt 0cm 5.4pt;\" width=\"300\">\n<p style=\"text-align: center; line-height: 200%; margin: 0cm 0cm 0.0001pt; font-size: 10.5pt; font-family: 等线;\" align=\"center\"><span style=\"font-size: 10.0pt; line-height: 200%; font-family: 微软雅黑, sans-serif; color: black;\">/</span></p>\n</td>\n</tr>\n<tr>\n<td style=\"width: 64.0pt; border-top: none; border-left: none; border-bottom: solid windowtext 1.0pt; border-right: solid windowtext 1.0pt; padding: 0cm 5.4pt 0cm 5.4pt;\" nowrap=\"nowrap\" width=\"85\">\n<p style=\"text-align: center; line-height: 200%; margin: 0cm 0cm 0.0001pt; font-size: 10.5pt; font-family: 等线;\" align=\"center\"><span style=\"font-size: 10.0pt; line-height: 200%; font-family: 微软雅黑, sans-serif; color: black;\">生活美容</span></p>\n</td>\n<td style=\"width: 176.3pt; border-top: none; border-left: none; border-bottom: solid windowtext 1.0pt; border-right: solid windowtext 1.0pt; padding: 0cm 5.4pt 0cm 5.4pt;\" width=\"41\">\n<p style=\"text-align: center; line-height: 21pt; margin: 0cm 0cm 0.0001pt; font-size: 10.5pt; font-family: 等线;\" align=\"center\"><span style=\"font-size: 10.0pt; font-family: 微软雅黑, sans-serif; color: black;\">/</span></p>\n</td>\n<td style=\"width: 225.25pt; border-top: none; border-left: none; border-bottom: solid windowtext 1.0pt; border-right: solid windowtext 1.0pt; padding: 0cm 5.4pt 0cm 5.4pt;\" width=\"300\">\n<p style=\"text-align: center; line-height: 21pt; margin: 0cm 0cm 0.0001pt; font-size: 10.5pt; font-family: 等线;\" align=\"center\"><span style=\"font-size: 10.0pt; font-family: 微软雅黑, sans-serif; color: black;\">许可项目不包含医疗（学）美容；符合《美容美发场所卫生规范》</span></p>\n</td>\n</tr>\n<tr>\n<td style=\"width: 64.0pt; border-top: none; border-left: none; border-bottom: solid windowtext 1.0pt; border-right: solid windowtext 1.0pt; padding: 0cm 5.4pt 0cm 5.4pt;\" nowrap=\"nowrap\" width=\"85\">\n<p style=\"text-align: center; line-height: 200%; margin: 0cm 0cm 0.0001pt; font-size: 10.5pt; font-family: 等线;\" align=\"center\"><span style=\"font-size: 10.0pt; line-height: 200%; font-family: 微软雅黑, sans-serif; color: black;\">细胞存储</span></p>\n</td>\n<td style=\"width: 176.3pt; border-top: none; border-left: none; border-bottom: solid windowtext 1.0pt; border-right: solid windowtext 1.0pt; padding: 0cm 5.4pt 0cm 5.4pt;\" width=\"41\">\n<p style=\"text-align: center; line-height: 21pt; margin: 0cm 0cm 0.0001pt; font-size: 10.5pt; font-family: 等线;\" align=\"center\"><span style=\"font-size: 10.0pt; font-family: 微软雅黑, sans-serif; color: black;\">《医疗机构执业许可证》</span></p>\n</td>\n<td style=\"width: 225.25pt; border-top: none; border-left: none; border-bottom: solid windowtext 1.0pt; border-right: solid windowtext 1.0pt; padding: 0cm 5.4pt 0cm 5.4pt;\" width=\"300\">\n<p style=\"text-align: center; line-height: 21pt; margin: 0cm 0cm 0.0001pt; font-size: 10.5pt; font-family: 等线;\" align=\"center\"><span style=\"font-size: 10.0pt; font-family: 微软雅黑, sans-serif; color: black;\">/</span></p>\n</td>\n</tr>\n<tr>\n<td style=\"width: 64.0pt; border-top: none; border-left: none; border-bottom: solid windowtext 1.0pt; border-right: solid windowtext 1.0pt; padding: 0cm 5.4pt 0cm 5.4pt;\" nowrap=\"nowrap\" width=\"85\">\n<p style=\"text-align: center; line-height: 200%; margin: 0cm 0cm 0.0001pt; font-size: 10.5pt; font-family: 等线;\" align=\"center\"><span style=\"font-size: 10.0pt; line-height: 200%; font-family: 微软雅黑, sans-serif;\">心理咨询</span></p>\n</td>\n<td style=\"width: 176.3pt; border-top: none; border-left: none; border-bottom: solid windowtext 1.0pt; border-right: solid windowtext 1.0pt; padding: 0cm 5.4pt 0cm 5.4pt;\" width=\"41\">\n<p style=\"text-align: center; line-height: 200%; margin: 0cm 0cm 0.0001pt; font-size: 10.5pt; font-family: 等线;\" align=\"center\"><span style=\"font-size: 10.0pt; line-height: 200%; font-family: 微软雅黑, sans-serif;\">《心理咨询师证书》</span></p>\n</td>\n<td style=\"width: 225.25pt; border-top: none; border-left: none; border-bottom: solid windowtext 1.0pt; border-right: solid windowtext 1.0pt; padding: 0cm 5.4pt 0cm 5.4pt;\" nowrap=\"nowrap\" width=\"300\">\n<p style=\"text-align: center; line-height: 200%; margin: 0cm 0cm 0.0001pt; font-size: 10.5pt; font-family: 等线;\" align=\"center\"><span style=\"font-size: 10.0pt; line-height: 200%; font-family: 微软雅黑, sans-serif; color: black;\">/</span></p>\n</td>\n</tr>\n<tr>\n<td style=\"width: 64.0pt; border-top: none; border-left: none; border-bottom: solid windowtext 1.0pt; border-right: solid windowtext 1.0pt; padding: 0cm 5.4pt 0cm 5.4pt;\" nowrap=\"nowrap\" width=\"85\">\n<p style=\"text-align: center; line-height: 200%; margin: 0cm 0cm 0.0001pt; font-size: 10.5pt; font-family: 等线;\" align=\"center\"><span style=\"font-size: 10.0pt; line-height: 200%; font-family: 微软雅黑, sans-serif; color: black;\">眼科服务</span></p>\n</td>\n<td style=\"width: 176.3pt; border-top: none; border-left: none; border-bottom: solid windowtext 1.0pt; border-right: solid windowtext 1.0pt; padding: 0cm 5.4pt 0cm 5.4pt;\" width=\"41\">\n<p style=\"text-align: center; line-height: 200%; margin: 0cm 0cm 0.0001pt; font-size: 10.5pt; font-family: 等线;\" align=\"center\"><span style=\"font-size: 10.0pt; line-height: 200%; font-family: 微软雅黑, sans-serif; color: black;\">《医疗机构执业许可证》</span></p>\n</td>\n<td style=\"width: 225.25pt; border-top: none; border-left: none; border-bottom: solid windowtext 1.0pt; border-right: solid windowtext 1.0pt; padding: 0cm 5.4pt 0cm 5.4pt;\" width=\"300\">\n<p style=\"text-align: center; line-height: 200%; margin: 0cm 0cm 0.0001pt; font-size: 10.5pt; font-family: 等线;\" align=\"center\"><span style=\"font-size: 10.0pt; line-height: 200%; font-family: 微软雅黑, sans-serif;\">如商品宣传出现医疗器械的名称和图片，需提供《医疗器械注册证》</span></p>\n</td>\n</tr>\n<tr>\n<td style=\"width: 64.0pt; border-top: none; border-left: none; border-bottom: solid windowtext 1.0pt; border-right: solid windowtext 1.0pt; padding: 0cm 5.4pt 0cm 5.4pt;\" nowrap=\"nowrap\" width=\"85\">\n<p style=\"text-align: center; line-height: 200%; margin: 0cm 0cm 0.0001pt; font-size: 10.5pt; font-family: 等线;\" align=\"center\"><span style=\"font-size: 10.0pt; line-height: 200%; font-family: 微软雅黑, sans-serif; color: black;\">医疗美容</span></p>\n</td>\n<td style=\"width: 176.3pt; border-top: none; border-left: none; border-bottom: solid windowtext 1.0pt; border-right: solid windowtext 1.0pt; padding: 0cm 5.4pt 0cm 5.4pt;\" width=\"41\">\n<p style=\"text-align: center; line-height: 200%; margin: 0cm 0cm 0.0001pt; font-size: 10.5pt; font-family: 等线;\" align=\"center\"><span style=\"font-size: 10.0pt; line-height: 200%; font-family: 微软雅黑, sans-serif; color: black;\">《医疗机构执业许可证》</span></p>\n</td>\n<td style=\"width: 225.25pt; border-top: none; border-left: none; border-bottom: solid windowtext 1.0pt; border-right: solid windowtext 1.0pt; padding: 0cm 5.4pt 0cm 5.4pt;\" width=\"300\">\n<p style=\"text-align: center; line-height: 200%; margin: 0cm 0cm 0.0001pt; font-size: 10.5pt; font-family: 等线;\" align=\"center\"><span style=\"font-size: 10.0pt; line-height: 200%; font-family: 微软雅黑, sans-serif;\">如商品宣传出现医疗器械的名称和图片，需提供《医疗器械注册证》</span></p>\n</td>\n</tr>\n<tr>\n<td style=\"width: 64.0pt; border-top: none; border-left: none; border-bottom: solid windowtext 1.0pt; border-right: solid windowtext 1.0pt; padding: 0cm 5.4pt 0cm 5.4pt;\" nowrap=\"nowrap\" width=\"85\">\n<p style=\"text-align: center; line-height: 200%; margin: 0cm 0cm 0.0001pt; font-size: 10.5pt; font-family: 等线;\" align=\"center\"><span style=\"font-size: 10.0pt; line-height: 200%; font-family: 微软雅黑, sans-serif; color: black;\">疫苗服务</span></p>\n</td>\n<td style=\"width: 176.3pt; border-top: none; border-left: none; border-bottom: solid windowtext 1.0pt; border-right: solid windowtext 1.0pt; padding: 0cm 5.4pt 0cm 5.4pt;\" width=\"41\">\n<p style=\"text-align: center; line-height: 200%; margin: 0cm 0cm 0.0001pt; font-size: 10.5pt; font-family: 等线;\" align=\"center\"><span style=\"font-size: 10.0pt; line-height: 200%; font-family: 微软雅黑, sans-serif; color: black;\">《医疗机构执业许可证》（公立机构可提供公示网站截图）</span></p>\n</td>\n<td style=\"width: 225.25pt; border-top: none; border-left: none; border-bottom: solid windowtext 1.0pt; border-right: solid windowtext 1.0pt; padding: 0cm 5.4pt 0cm 5.4pt;\" width=\"300\">\n<p style=\"text-align: center; margin: 0cm 0cm 0.0001pt; font-size: 10.5pt; font-family: 等线;\" align=\"center\"><span style=\"font-size: 10.0pt; font-family: 微软雅黑, sans-serif; color: black;\">/</span></p>\n</td>\n</tr>\n<tr>\n<td style=\"width: 64.0pt; border-top: none; border-left: none; border-bottom: solid windowtext 1.0pt; border-right: solid windowtext 1.0pt; padding: 0cm 5.4pt 0cm 5.4pt;\" nowrap=\"nowrap\" width=\"85\">\n<p style=\"text-align: center; line-height: 200%; margin: 0cm 0cm 0.0001pt; font-size: 10.5pt; font-family: 等线;\" align=\"center\"><span style=\"font-size: 10.0pt; line-height: 200%; font-family: 微软雅黑, sans-serif; color: black;\">孕产服务</span></p>\n</td>\n<td style=\"width: 176.3pt; border-top: none; border-left: none; border-bottom: solid windowtext 1.0pt; border-right: solid windowtext 1.0pt; padding: 0cm 5.4pt 0cm 5.4pt;\" width=\"41\">\n<p style=\"text-align: center; line-height: 200%; margin: 0cm 0cm 0.0001pt; font-size: 10.5pt; font-family: 等线;\" align=\"center\"><span style=\"font-size: 10.0pt; line-height: 200%; font-family: 微软雅黑, sans-serif; color: black;\">《医疗机构执业许可证》</span></p>\n</td>\n<td style=\"width: 225.25pt; border-top: none; border-left: none; border-bottom: solid windowtext 1.0pt; border-right: solid windowtext 1.0pt; padding: 0cm 5.4pt 0cm 5.4pt;\" nowrap=\"nowrap\" width=\"300\">\n<p style=\"text-align: center; margin: 0cm 0cm 0.0001pt; font-size: 10.5pt; font-family: 等线;\" align=\"center\"><span style=\"font-size: 10.0pt; font-family: 微软雅黑, sans-serif; color: black;\">/</span></p>\n</td>\n</tr>\n<tr>\n<td style=\"width: 64.0pt; border-top: none; border-left: none; border-bottom: solid windowtext 1.0pt; border-right: solid windowtext 1.0pt; padding: 0cm 5.4pt 0cm 5.4pt;\" nowrap=\"nowrap\" width=\"85\">\n<p style=\"text-align: center; line-height: 200%; margin: 0cm 0cm 0.0001pt; font-size: 10.5pt; font-family: 等线;\" align=\"center\"><span style=\"font-size: 10.0pt; line-height: 200%; font-family: 微软雅黑, sans-serif; color: black;\">中医服务</span></p>\n</td>\n<td style=\"width: 176.3pt; border-top: none; border-left: none; border-bottom: solid windowtext 1.0pt; border-right: solid windowtext 1.0pt; padding: 0cm 5.4pt 0cm 5.4pt;\" width=\"41\">\n<p style=\"text-align: center; line-height: 200%; margin: 0cm 0cm 0.0001pt; font-size: 10.5pt; font-family: 等线;\" align=\"center\"><span style=\"font-size: 10.0pt; line-height: 200%; font-family: 微软雅黑, sans-serif; color: black;\">《医疗机构执业许可证》/中医诊所备案</span></p>\n</td>\n<td style=\"width: 225.25pt; border-top: none; border-left: none; border-bottom: solid windowtext 1.0pt; border-right: solid windowtext 1.0pt; padding: 0cm 5.4pt 0cm 5.4pt;\" width=\"300\">\n<p style=\"text-align: center; line-height: 200%; margin: 0cm 0cm 0.0001pt; font-size: 10.5pt; font-family: 等线;\" align=\"center\"><span style=\"font-size: 10.0pt; line-height: 200%; font-family: 微软雅黑, sans-serif; color: black;\">/</span></p>\n</td>\n</tr>\n<tr>\n<td style=\"width: 696.9pt; border: solid windowtext 1.0pt; border-top: none; padding: 0cm 0cm 0cm 0cm;\" colspan=\"5\" width=\"531\">\n<p style=\"margin: 0cm 0cm 0.0001pt 6.6pt; line-height: 200%; background: white; text-align: justify; font-size: 10.5pt; font-family: 等线;\"><span style=\"font-size: 10.0pt; line-height: 200%; font-family: 微软雅黑, sans-serif; color: black;\">1. </span><span style=\"font-size: 10.0pt; line-height: 200%; font-family: 微软雅黑, sans-serif; color: black;\">旗舰店授权书模板：</span><a href=\"https://helpcenter.jd.com/vender/issue/926-4279.html\"><span style=\"font-size: 10.0pt; line-height: 200%; font-family: 微软雅黑, sans-serif; color: blue;\">旗舰店授权书模板</span></a></p>\n<p style=\"margin: 0cm 0cm 0.0001pt 6.6pt; line-height: 200%; background: white; text-align: justify; font-size: 10.5pt; font-family: 等线;\"><span style=\"font-size: 10.0pt; line-height: 200%; font-family: 微软雅黑, sans-serif; color: black;\">2. </span><span style=\"font-size: 10.0pt; line-height: 200%; font-family: 微软雅黑, sans-serif; color: black;\">卖场店授权书模板：</span><a href=\"https://helpcenter.jd.com/vender/issue/1000-44485.html\" target=\"_blank\" rel=\"noopener\"><span style=\"font-size: 10.0pt; line-height: 200%; font-family: 微软雅黑, sans-serif; color: blue;\">卖场店授权模板</span></a></p>\n<p style=\"margin: 0cm 0cm 0.0001pt 6.6pt; line-height: 200%; background: white; text-align: justify; font-size: 10.5pt; font-family: 等线;\"><span style=\"font-size: 10.0pt; line-height: 200%; font-family: 微软雅黑, sans-serif; color: black;\">3. </span><span style=\"font-size: 10.0pt; line-height: 200%; font-family: 微软雅黑, sans-serif; color: black;\">京东开放平台各类目资费一览表：</span><a href=\"https://rule.jd.com/rule/ruleDetail.action?ruleId=638209647311982592&amp;type=0&amp;btype=1\"><span style=\"font-size: 10.0pt; line-height: 200%; font-family: 微软雅黑, sans-serif; color: blue;\">京东开放平台类目资费规则</span></a></p>\n<p style=\"margin: 0cm 0cm 0.0001pt 6.6pt; line-height: 200%; background: white; text-align: justify; font-size: 10.5pt; font-family: 等线;\"><span style=\"font-size: 10.0pt; line-height: 200%; font-family: 微软雅黑, sans-serif; color: black;\">4. </span><span style=\"font-size: 10.0pt; line-height: 200%; font-family: 微软雅黑, sans-serif; color: black;\">店铺命</span><span style=\"font-size: 10.0pt; line-height: 200%; font-family: 微软雅黑, sans-serif;\">名规则：</span><a href=\"https://rule.jd.com/rule/ruleDetail.action?ruleId=2598\" target=\"_blank\" rel=\"noopener\"><span style=\"font-size: 10.0pt; line-height: 200%; font-family: 微软雅黑, sans-serif; color: blue;\">https://rule.jd.com/rule/ruleDetail.action?ruleId=2598</span></a></p>\n</td>\n</tr>\n</tbody>\n</table>\n<p style=\"line-height: 200%; background: white; margin: 0cm 0cm 0.0001pt; text-align: justify; font-size: 10.5pt; font-family: 等线;\"><strong><span style=\"font-size: 10.0pt; line-height: 200%; font-family: 微软雅黑, sans-serif; color: black;\">附则</span></strong></p>\n<p style=\"text-align: left; line-height: 200%; background: white; margin: 0cm 0cm 0.0001pt; font-size: 10.5pt; font-family: 等线;\" align=\"left\"><span style=\"font-size: 10.0pt; line-height: 200%; font-family: 微软雅黑, sans-serif; color: black;\">1. </span><span style=\"font-size: 10.0pt; line-height: 200%; font-family: 微软雅黑, sans-serif; color: black;\">京东商家的行为，发生在本管理规则生效之日以前的，适用当时的规则。发生在本管理规则生效之日以后的，适用本规则。</span></p>\n<p style=\"text-align: left; line-height: 200%; background: white; margin: 0cm 0cm 0.0001pt; font-size: 10.5pt; font-family: 等线;\" align=\"left\"><span style=\"font-size: 10.0pt; line-height: 200%; font-family: 微软雅黑, sans-serif; color: black;\">2. </span><span style=\"font-size: 10.0pt; line-height: 200%; font-family: 微软雅黑, sans-serif; color: black;\">京东可根据平台运营情况随时调整本管理规则并以公告的形式向商家公示。</span></p>\n<p style=\"text-align: left; line-height: 200%; background: white; margin: 0cm 0cm 0.0001pt; font-size: 10.5pt; font-family: 等线;\" align=\"left\"><span style=\"font-size: 10.0pt; line-height: 200%; font-family: 微软雅黑, sans-serif; color: black;\">3. </span><span style=\"font-size: 10.0pt; line-height: 200%; font-family: 微软雅黑, sans-serif; color: black;\">商家应遵守国家法律、行政法规、部门规章等规范性文件。对任何涉嫌违反国家法律、行政法规、部门规章等规范性文件的行为，本规则已有规定的，适用于本规则。本规则尚无规定的，京东有权酌情处理。但京东对商家的处理不免除其应承担的法律责任。商家在京东的任何行为，应同时遵守与京东及其关联公司签订的各项协议。</span></p>\n<p style=\"text-align: left; line-height: 200%; background: white; margin: 0cm 0cm 0.0001pt; font-size: 10.5pt; font-family: 等线;\" align=\"left\"><span style=\"font-size: 10.0pt; line-height: 200%; font-family: 微软雅黑, sans-serif; color: black;\">4. </span><span style=\"font-size: 10.0pt; line-height: 200%; font-family: 微软雅黑, sans-serif; color: black;\">本规则标准于2024年11月19日修订，于2024年11月26日生效。</span></p>",
    "selectCategoryId": [
      "373",
      "393"
    ],
    "categoryIdPath": "373,393",
    "top": "0",
    "jfsContentUrl": "//storage.jd.com/karmavender/file/scene/20241119/08718cca14da4c5c98d239d6dd35d7ab.txt",
    "pdfFileUrl": "//storage.jd.com/karmavender/file/pdf/20241119/9baa48d7e708456ebf9281a6e6a5cf51.pdf",
    "showCollect": false,
    "hideCollectButton": true,
    "id": "907471114710683648",
    "summary": "京东开放平台健康服务类目资质标准",
    "uv": "1",
    "solvePin": "liufurong6",
    "changeReason": "调整TM标注册时间限制",
    "preRuleId": "907471693356863488",
    "activeTime": 1732550400000,
    "multiCategoryId": "",
    "solveDept": "京东集团-京东健康-公共事务与合规部-合规治理部-规则治理部",
    "updateUser": "wanghuanhuan655",
    "updateTime": 1731983174000,
    "keyWord": "京东开放平台健康服务类目资质标准",
    "allLabelIds": "",
    "preRuleTitle": "京东开放平台营养保健类目资质标准",
    "createTime": 1667964373000,
    "followRuleTitle": "京东开放平台传统滋补类目资质标准",
    "createUser": "yanhaojun5",
    "businessType": 1,
    "categoryId": "393",
    "status": 1
  }
}